Workbook

Sheet Summary
A1: Summary — Market Garden Bed Allocation
A2: perfect-competition engagement · marginal-analysis capability · see Solver tab to change the allocation
A4: Allocation (Solver optimum)
A5: Crop | B5: Beds | C5: Price/bed | D5: Fertilizer/bed | E5: Revenue
A6: Tomato | B6: =Calculations!$E$39 | C6: =Tomato_Price | D6: =Tomato_Fertilizer_Per_Bed | E6: =B6*C6
A7: Carrot | B7: =Calculations!$E$40 | C7: =Carrot_Price | D7: =Carrot_Fertilizer_Per_Bed | E7: =B7*C7
A8: Mesclun | B8: =Calculations!$E$41 | C8: =Mesclun_Price | D8: =Mesclun_Fertilizer_Per_Bed | E8: =B8*C8
A9: Total beds | B9: =SUM(B6:B8)
A11: Labor & Cost Summary
A12: Temp workers hired | D12: =Calculations!$E$42
A13: Total labor hours needed | D13: =Calculations!$E$46
A14: Revenue | D14: =Calculations!$E$50
A15: Fertilizer cost | D15: =Calculations!$E$51
A16: Labor cost (tiered) | D16: =Calculations!$E$49
A17: Total Contribution | D17: =Calculations!$E$52
A18: Fixed Cost | D18: =Fixed_Cost
A19: PROFIT | D19: =Calculations!$E$53
A21: Greedy P=MC Walk vs. Solver (spec §5/§9)
A22: Greedy walk beds — Tomato / Carrot / Mesclun | C22: =Calculations!$D$148 | D22: =Calculations!$E$148 | E22: =Calculations!$F$148
A23: Greedy walk PROFIT | D23: =Calculations!$D$152
A24: Delta vs. Solver PROFIT | D24: =Calculations!$D$153
A26: Hypothesis Verdict (spec §7/§9)
A27: Check 1 — Carrots > Mesclun beds? | D27: =Calculations!$E$66
A28: Check 5 — Swap test (Mesclun-1/Carrot+1) verdict | D28: =Calculations!$E$75
A29: Checks 2-4 require manual re-runs — see Notes tab.

Sheet Inputs
A1: Inputs — Market Garden Bed Allocation (v1.5)
A2: capabilities/marginal-analysis · perfect-competition engagement · edit only the yellow cells
A4: Category | B4: Named Range | C4: Value | D4: Unit
A5: Bed capacity | B5: Total_Beds | C5: 64 | D5: beds
B6: Tomato_Bed_Cap | C6: 20 | D6: beds
B7: Carrot_Bed_Cap | C7: 20 | D7: beds
B8: Mesclun_Bed_Cap | C8: 30 | D8: beds
A9: Season | B9: Season_Weeks | C9: 36 | D9: weeks
A10: Fixed costs | B10: Fixed_Cost | C10: 20000 | D10: $
A11: Labor pool | B11: Farmer_Season_Salary | C11: 50000 | D11: $/season
B12: Farmer_Implied_Wage | C12: =Farmer_Season_Salary/2/Own_Labor_Hours | D12: $/hr
B13: Own_Labor_Hours | C13: 720 | D13: hrs
B14: Temp_Worker_Max | C14: 4 | D14: workers
B15: Temp_Worker_Hours | C15: 1440 | D15: hrs/worker
B16: Temp_Worker_Flat_Cost | C16: 25000 | D16: $/worker
B17: Temp_Wage_Per_Hour | C17: =Temp_Worker_Flat_Cost/Temp_Worker_Hours | D17: $/hr
A18: Crop economics | B18: Tomato_Price | C18: 8800 | D18: $/bed
B19: Carrot_Price | C19: 2094 | D19: $/bed
B20: Mesclun_Price | C20: 2700 | D20: $/bed
B21: Tomato_Fertilizer_Per_Bed | C21: 880 | D21: $/bed
B22: Carrot_Fertilizer_Per_Bed | C22: 440 | D22: $/bed
B23: Mesclun_Fertilizer_Per_Bed | C23: 880 | D23: $/bed
B24: Tomato_Base_Labor_Hrs_Wk_Bed | C24: 2.5 | D24: hrs/wk/bed
B25: Carrot_Base_Labor_Hrs_Wk_Bed | C25: =C24/3 | D25: hrs/wk/bed
B26: Mesclun_Base_Labor_Hrs_Wk_Bed | C26: 1.25 | D26: hrs/wk/bed
B27: Tomato_Diminishing_Rate | C27: 0.1 | D27: %/bed
B28: Carrot_Diminishing_Rate | C28: 0.025 | D28: %/bed
B29: Mesclun_Diminishing_Rate | C29: 0.0125 | D29: %/bed

Sheet Calculations
A1: Calculations — Per-Crop Marginal Cost Curves (standalone)
A2: Standalone view: each crop's OWN cumulative hours determine which wage tier it's in (spec §5) -- first Own_Labor_Hours (720) of THAT CROP's hours are the expensive Farmer_Implied_Wage tier, rest are the cheaper Temp_Wage_Per_Hour tier. This is a sanity-check reference, not the joint answer (the Joint Allocation section below uses the real shared pool).
B3: Tomato | I3: Carrot | P3: Mesclun
B4: Bed # | C4: Marginal Hrs | D4: Cumulative Hrs | E4: Marg. Cost (standalone) | F4: Marg. Contribution | G4: Cumul. Contribution | H4: Still profitable? | I4: Bed # | J4: Marginal Hrs | K4: Cumulative Hrs | L4: Marg. Cost (standalone) | M4: Marg. Contribution | N4: Cumul. Contribution | O4: Still profitable? | P4: Bed # | Q4: Marginal Hrs | R4: Cumulative Hrs | S4: Marg. Cost (standalone) | T4: Marg. Contribution | U4: Cumul. Contribution | V4: Still profitable?
B5: =ROW()-4 | C5: =(B5*Tomato_Base_Labor_Hrs_Wk_Bed*Season_Weeks*(1+Tomato_Diminishing_Rate)^B5)-((B5-1)*Tomato_Base_Labor_Hrs_Wk_Bed*Season_Weeks*(1+Tomato_Diminishing_Rate)^(B5-1)) | D5: =SUM($C$5:C5) | E5: =MAX(0,MIN(D5,Own_Labor_Hours)-MIN((D5-C5),Own_Labor_Hours))*Farmer_Implied_Wage+(C5-MAX(0,MIN(D5,Own_Labor_Hours)-MIN((D5-C5),Own_Labor_Hours)))*Temp_Wage_Per_Hour+Tomato_Fertilizer_Per_Bed | F5: =Tomato_Price-E5 | G5: =SUM($F$5:F5) | H5: =AND(TRUE(),F5>=0) | I5: =ROW()-4 | J5: =(I5*Carrot_Base_Labor_Hrs_Wk_Bed*Season_Weeks*(1+Carrot_Diminishing_Rate)^I5)-((I5-1)*Carrot_Base_Labor_Hrs_Wk_Bed*Season_Weeks*(1+Carrot_Diminishing_Rate)^(I5-1)) | K5: =SUM($J$5:J5) | L5: =MAX(0,MIN(K5,Own_Labor_Hours)-MIN((K5-J5),Own_Labor_Hours))*Farmer_Implied_Wage+(J5-MAX(0,MIN(K5,Own_Labor_Hours)-MIN((K5-J5),Own_Labor_Hours)))*Temp_Wage_Per_Hour+Carrot_Fertilizer_Per_Bed | M5: =Carrot_Price-L5 | N5: =SUM($M$5:M5) | O5: =AND(TRUE(),M5>=0) | P5: =ROW()-4 | Q5: =(P5*Mesclun_Base_Labor_Hrs_Wk_Bed*Season_Weeks*(1+Mesclun_Diminishing_Rate)^P5)-((P5-1)*Mesclun_Base_Labor_Hrs_Wk_Bed*Season_Weeks*(1+Mesclun_Diminishing_Rate)^(P5-1)) | R5: =SUM($Q$5:Q5) | S5: =MAX(0,MIN(R5,Own_Labor_Hours)-MIN((R5-Q5),Own_Labor_Hours))*Farmer_Implied_Wage+(Q5-MAX(0,MIN(R5,Own_Labor_Hours)-MIN((R5-Q5),Own_Labor_Hours)))*Temp_Wage_Per_Hour+Mesclun_Fertilizer_Per_Bed | T5: =Mesclun_Price-S5 | U5: =SUM($T$5:T5) | V5: =AND(TRUE(),T5>=0)
B6: =ROW()-4 | C6: =(B6*Tomato_Base_Labor_Hrs_Wk_Bed*Season_Weeks*(1+Tomato_Diminishing_Rate)^B6)-((B6-1)*Tomato_Base_Labor_Hrs_Wk_Bed*Season_Weeks*(1+Tomato_Diminishing_Rate)^(B6-1)) | D6: =SUM($C$5:C6) | E6: =MAX(0,MIN(D6,Own_Labor_Hours)-MIN((D6-C6),Own_Labor_Hours))*Farmer_Implied_Wage+(C6-MAX(0,MIN(D6,Own_Labor_Hours)-MIN((D6-C6),Own_Labor_Hours)))*Temp_Wage_Per_Hour+Tomato_Fertilizer_Per_Bed | F6: =Tomato_Price-E6 | G6: =SUM($F$5:F6) | H6: =AND(H5,F6>=0) | I6: =ROW()-4 | J6: =(I6*Carrot_Base_Labor_Hrs_Wk_Bed*Season_Weeks*(1+Carrot_Diminishing_Rate)^I6)-((I6-1)*Carrot_Base_Labor_Hrs_Wk_Bed*Season_Weeks*(1+Carrot_Diminishing_Rate)^(I6-1)) | K6: =SUM($J$5:J6) | L6: =MAX(0,MIN(K6,Own_Labor_Hours)-MIN((K6-J6),Own_Labor_Hours))*Farmer_Implied_Wage+(J6-MAX(0,MIN(K6,Own_Labor_Hours)-MIN((K6-J6),Own_Labor_Hours)))*Temp_Wage_Per_Hour+Carrot_Fertilizer_Per_Bed | M6: =Carrot_Price-L6 | N6: =SUM($M$5:M6) | O6: =AND(O5,M6>=0) | P6: =ROW()-4 | Q6: =(P6*Mesclun_Base_Labor_Hrs_Wk_Bed*Season_Weeks*(1+Mesclun_Diminishing_Rate)^P6)-((P6-1)*Mesclun_Base_Labor_Hrs_Wk_Bed*Season_Weeks*(1+Mesclun_Diminishing_Rate)^(P6-1)) | R6: =SUM($Q$5:Q6) | S6: =MAX(0,MIN(R6,Own_Labor_Hours)-MIN((R6-Q6),Own_Labor_Hours))*Farmer_Implied_Wage+(Q6-MAX(0,MIN(R6,Own_Labor_Hours)-MIN((R6-Q6),Own_Labor_Hours)))*Temp_Wage_Per_Hour+Mesclun_Fertilizer_Per_Bed | T6: =Mesclun_Price-S6 | U6: =SUM($T$5:T6) | V6: =AND(V5,T6>=0)
B7: =ROW()-4 | C7: =(B7*Tomato_Base_Labor_Hrs_Wk_Bed*Season_Weeks*(1+Tomato_Diminishing_Rate)^B7)-((B7-1)*Tomato_Base_Labor_Hrs_Wk_Bed*Season_Weeks*(1+Tomato_Diminishing_Rate)^(B7-1)) | D7: =SUM($C$5:C7) | E7: =MAX(0,MIN(D7,Own_Labor_Hours)-MIN((D7-C7),Own_Labor_Hours))*Farmer_Implied_Wage+(C7-MAX(0,MIN(D7,Own_Labor_Hours)-MIN((D7-C7),Own_Labor_Hours)))*Temp_Wage_Per_Hour+Tomato_Fertilizer_Per_Bed | F7: =Tomato_Price-E7 | G7: =SUM($F$5:F7) | H7: =AND(H6,F7>=0) | I7: =ROW()-4 | J7: =(I7*Carrot_Base_Labor_Hrs_Wk_Bed*Season_Weeks*(1+Carrot_Diminishing_Rate)^I7)-((I7-1)*Carrot_Base_Labor_Hrs_Wk_Bed*Season_Weeks*(1+Carrot_Diminishing_Rate)^(I7-1)) | K7: =SUM($J$5:J7) | L7: =MAX(0,MIN(K7,Own_Labor_Hours)-MIN((K7-J7),Own_Labor_Hours))*Farmer_Implied_Wage+(J7-MAX(0,MIN(K7,Own_Labor_Hours)-MIN((K7-J7),Own_Labor_Hours)))*Temp_Wage_Per_Hour+Carrot_Fertilizer_Per_Bed | M7: =Carrot_Price-L7 | N7: =SUM($M$5:M7) | O7: =AND(O6,M7>=0) | P7: =ROW()-4 | Q7: =(P7*Mesclun_Base_Labor_Hrs_Wk_Bed*Season_Weeks*(1+Mesclun_Diminishing_Rate)^P7)-((P7-1)*Mesclun_Base_Labor_Hrs_Wk_Bed*Season_Weeks*(1+Mesclun_Diminishing_Rate)^(P7-1)) | R7: =SUM($Q$5:Q7) | S7: =MAX(0,MIN(R7,Own_Labor_Hours)-MIN((R7-Q7),Own_Labor_Hours))*Farmer_Implied_Wage+(Q7-MAX(0,MIN(R7,Own_Labor_Hours)-MIN((R7-Q7),Own_Labor_Hours)))*Temp_Wage_Per_Hour+Mesclun_Fertilizer_Per_Bed | T7: =Mesclun_Price-S7 | U7: =SUM($T$5:T7) | V7: =AND(V6,T7>=0)
B8: =ROW()-4 | C8: =(B8*Tomato_Base_Labor_Hrs_Wk_Bed*Season_Weeks*(1+Tomato_Diminishing_Rate)^B8)-((B8-1)*Tomato_Base_Labor_Hrs_Wk_Bed*Season_Weeks*(1+Tomato_Diminishing_Rate)^(B8-1)) | D8: =SUM($C$5:C8) | E8: =MAX(0,MIN(D8,Own_Labor_Hours)-MIN((D8-C8),Own_Labor_Hours))*Farmer_Implied_Wage+(C8-MAX(0,MIN(D8,Own_Labor_Hours)-MIN((D8-C8),Own_Labor_Hours)))*Temp_Wage_Per_Hour+Tomato_Fertilizer_Per_Bed | F8: =Tomato_Price-E8 | G8: =SUM($F$5:F8) | H8: =AND(H7,F8>=0) | I8: =ROW()-4 | J8: =(I8*Carrot_Base_Labor_Hrs_Wk_Bed*Season_Weeks*(1+Carrot_Diminishing_Rate)^I8)-((I8-1)*Carrot_Base_Labor_Hrs_Wk_Bed*Season_Weeks*(1+Carrot_Diminishing_Rate)^(I8-1)) | K8: =SUM($J$5:J8) | L8: =MAX(0,MIN(K8,Own_Labor_Hours)-MIN((K8-J8),Own_Labor_Hours))*Farmer_Implied_Wage+(J8-MAX(0,MIN(K8,Own_Labor_Hours)-MIN((K8-J8),Own_Labor_Hours)))*Temp_Wage_Per_Hour+Carrot_Fertilizer_Per_Bed | M8: =Carrot_Price-L8 | N8: =SUM($M$5:M8) | O8: =AND(O7,M8>=0) | P8: =ROW()-4 | Q8: =(P8*Mesclun_Base_Labor_Hrs_Wk_Bed*Season_Weeks*(1+Mesclun_Diminishing_Rate)^P8)-((P8-1)*Mesclun_Base_Labor_Hrs_Wk_Bed*Season_Weeks*(1+Mesclun_Diminishing_Rate)^(P8-1)) | R8: =SUM($Q$5:Q8) | S8: =MAX(0,MIN(R8,Own_Labor_Hours)-MIN((R8-Q8),Own_Labor_Hours))*Farmer_Implied_Wage+(Q8-MAX(0,MIN(R8,Own_Labor_Hours)-MIN((R8-Q8),Own_Labor_Hours)))*Temp_Wage_Per_Hour+Mesclun_Fertilizer_Per_Bed | T8: =Mesclun_Price-S8 | U8: =SUM($T$5:T8) | V8: =AND(V7,T8>=0)
B9: =ROW()-4 | C9: =(B9*Tomato_Base_Labor_Hrs_Wk_Bed*Season_Weeks*(1+Tomato_Diminishing_Rate)^B9)-((B9-1)*Tomato_Base_Labor_Hrs_Wk_Bed*Season_Weeks*(1+Tomato_Diminishing_Rate)^(B9-1)) | D9: =SUM($C$5:C9) | E9: =MAX(0,MIN(D9,Own_Labor_Hours)-MIN((D9-C9),Own_Labor_Hours))*Farmer_Implied_Wage+(C9-MAX(0,MIN(D9,Own_Labor_Hours)-MIN((D9-C9),Own_Labor_Hours)))*Temp_Wage_Per_Hour+Tomato_Fertilizer_Per_Bed | F9: =Tomato_Price-E9 | G9: =SUM($F$5:F9) | H9: =AND(H8,F9>=0) | I9: =ROW()-4 | J9: =(I9*Carrot_Base_Labor_Hrs_Wk_Bed*Season_Weeks*(1+Carrot_Diminishing_Rate)^I9)-((I9-1)*Carrot_Base_Labor_Hrs_Wk_Bed*Season_Weeks*(1+Carrot_Diminishing_Rate)^(I9-1)) | K9: =SUM($J$5:J9) | L9: =MAX(0,MIN(K9,Own_Labor_Hours)-MIN((K9-J9),Own_Labor_Hours))*Farmer_Implied_Wage+(J9-MAX(0,MIN(K9,Own_Labor_Hours)-MIN((K9-J9),Own_Labor_Hours)))*Temp_Wage_Per_Hour+Carrot_Fertilizer_Per_Bed | M9: =Carrot_Price-L9 | N9: =SUM($M$5:M9) | O9: =AND(O8,M9>=0) | P9: =ROW()-4 | Q9: =(P9*Mesclun_Base_Labor_Hrs_Wk_Bed*Season_Weeks*(1+Mesclun_Diminishing_Rate)^P9)-((P9-1)*Mesclun_Base_Labor_Hrs_Wk_Bed*Season_Weeks*(1+Mesclun_Diminishing_Rate)^(P9-1)) | R9: =SUM($Q$5:Q9) | S9: =MAX(0,MIN(R9,Own_Labor_Hours)-MIN((R9-Q9),Own_Labor_Hours))*Farmer_Implied_Wage+(Q9-MAX(0,MIN(R9,Own_Labor_Hours)-MIN((R9-Q9),Own_Labor_Hours)))*Temp_Wage_Per_Hour+Mesclun_Fertilizer_Per_Bed | T9: =Mesclun_Price-S9 | U9: =SUM($T$5:T9) | V9: =AND(V8,T9>=0)
B10: =ROW()-4 | C10: =(B10*Tomato_Base_Labor_Hrs_Wk_Bed*Season_Weeks*(1+Tomato_Diminishing_Rate)^B10)-((B10-1)*Tomato_Base_Labor_Hrs_Wk_Bed*Season_Weeks*(1+Tomato_Diminishing_Rate)^(B10-1)) | D10: =SUM($C$5:C10) | E10: =MAX(0,MIN(D10,Own_Labor_Hours)-MIN((D10-C10),Own_Labor_Hours))*Farmer_Implied_Wage+(C10-MAX(0,MIN(D10,Own_Labor_Hours)-MIN((D10-C10),Own_Labor_Hours)))*Temp_Wage_Per_Hour+Tomato_Fertilizer_Per_Bed | F10: =Tomato_Price-E10 | G10: =SUM($F$5:F10) | H10: =AND(H9,F10>=0) | I10: =ROW()-4 | J10: =(I10*Carrot_Base_Labor_Hrs_Wk_Bed*Season_Weeks*(1+Carrot_Diminishing_Rate)^I10)-((I10-1)*Carrot_Base_Labor_Hrs_Wk_Bed*Season_Weeks*(1+Carrot_Diminishing_Rate)^(I10-1)) | K10: =SUM($J$5:J10) | L10: =MAX(0,MIN(K10,Own_Labor_Hours)-MIN((K10-J10),Own_Labor_Hours))*Farmer_Implied_Wage+(J10-MAX(0,MIN(K10,Own_Labor_Hours)-MIN((K10-J10),Own_Labor_Hours)))*Temp_Wage_Per_Hour+Carrot_Fertilizer_Per_Bed | M10: =Carrot_Price-L10 | N10: =SUM($M$5:M10) | O10: =AND(O9,M10>=0) | P10: =ROW()-4 | Q10: =(P10*Mesclun_Base_Labor_Hrs_Wk_Bed*Season_Weeks*(1+Mesclun_Diminishing_Rate)^P10)-((P10-1)*Mesclun_Base_Labor_Hrs_Wk_Bed*Season_Weeks*(1+Mesclun_Diminishing_Rate)^(P10-1)) | R10: =SUM($Q$5:Q10) | S10: =MAX(0,MIN(R10,Own_Labor_Hours)-MIN((R10-Q10),Own_Labor_Hours))*Farmer_Implied_Wage+(Q10-MAX(0,MIN(R10,Own_Labor_Hours)-MIN((R10-Q10),Own_Labor_Hours)))*Temp_Wage_Per_Hour+Mesclun_Fertilizer_Per_Bed | T10: =Mesclun_Price-S10 | U10: =SUM($T$5:T10) | V10: =AND(V9,T10>=0)
B11: =ROW()-4 | C11: =(B11*Tomato_Base_Labor_Hrs_Wk_Bed*Season_Weeks*(1+Tomato_Diminishing_Rate)^B11)-((B11-1)*Tomato_Base_Labor_Hrs_Wk_Bed*Season_Weeks*(1+Tomato_Diminishing_Rate)^(B11-1)) | D11: =SUM($C$5:C11) | E11: =MAX(0,MIN(D11,Own_Labor_Hours)-MIN((D11-C11),Own_Labor_Hours))*Farmer_Implied_Wage+(C11-MAX(0,MIN(D11,Own_Labor_Hours)-MIN((D11-C11),Own_Labor_Hours)))*Temp_Wage_Per_Hour+Tomato_Fertilizer_Per_Bed | F11: =Tomato_Price-E11 | G11: =SUM($F$5:F11) | H11: =AND(H10,F11>=0) | I11: =ROW()-4 | J11: =(I11*Carrot_Base_Labor_Hrs_Wk_Bed*Season_Weeks*(1+Carrot_Diminishing_Rate)^I11)-((I11-1)*Carrot_Base_Labor_Hrs_Wk_Bed*Season_Weeks*(1+Carrot_Diminishing_Rate)^(I11-1)) | K11: =SUM($J$5:J11) | L11: =MAX(0,MIN(K11,Own_Labor_Hours)-MIN((K11-J11),Own_Labor_Hours))*Farmer_Implied_Wage+(J11-MAX(0,MIN(K11,Own_Labor_Hours)-MIN((K11-J11),Own_Labor_Hours)))*Temp_Wage_Per_Hour+Carrot_Fertilizer_Per_Bed | M11: =Carrot_Price-L11 | N11: =SUM($M$5:M11) | O11: =AND(O10,M11>=0) | P11: =ROW()-4 | Q11: =(P11*Mesclun_Base_Labor_Hrs_Wk_Bed*Season_Weeks*(1+Mesclun_Diminishing_Rate)^P11)-((P11-1)*Mesclun_Base_Labor_Hrs_Wk_Bed*Season_Weeks*(1+Mesclun_Diminishing_Rate)^(P11-1)) | R11: =SUM($Q$5:Q11) | S11: =MAX(0,MIN(R11,Own_Labor_Hours)-MIN((R11-Q11),Own_Labor_Hours))*Farmer_Implied_Wage+(Q11-MAX(0,MIN(R11,Own_Labor_Hours)-MIN((R11-Q11),Own_Labor_Hours)))*Temp_Wage_Per_Hour+Mesclun_Fertilizer_Per_Bed | T11: =Mesclun_Price-S11 | U11: =SUM($T$5:T11) | V11: =AND(V10,T11>=0)
B12: =ROW()-4 | C12: =(B12*Tomato_Base_Labor_Hrs_Wk_Bed*Season_Weeks*(1+Tomato_Diminishing_Rate)^B12)-((B12-1)*Tomato_Base_Labor_Hrs_Wk_Bed*Season_Weeks*(1+Tomato_Diminishing_Rate)^(B12-1)) | D12: =SUM($C$5:C12) | E12: =MAX(0,MIN(D12,Own_Labor_Hours)-MIN((D12-C12),Own_Labor_Hours))*Farmer_Implied_Wage+(C12-MAX(0,MIN(D12,Own_Labor_Hours)-MIN((D12-C12),Own_Labor_Hours)))*Temp_Wage_Per_Hour+Tomato_Fertilizer_Per_Bed | F12: =Tomato_Price-E12 | G12: =SUM($F$5:F12) | H12: =AND(H11,F12>=0) | I12: =ROW()-4 | J12: =(I12*Carrot_Base_Labor_Hrs_Wk_Bed*Season_Weeks*(1+Carrot_Diminishing_Rate)^I12)-((I12-1)*Carrot_Base_Labor_Hrs_Wk_Bed*Season_Weeks*(1+Carrot_Diminishing_Rate)^(I12-1)) | K12: =SUM($J$5:J12) | L12: =MAX(0,MIN(K12,Own_Labor_Hours)-MIN((K12-J12),Own_Labor_Hours))*Farmer_Implied_Wage+(J12-MAX(0,MIN(K12,Own_Labor_Hours)-MIN((K12-J12),Own_Labor_Hours)))*Temp_Wage_Per_Hour+Carrot_Fertilizer_Per_Bed | M12: =Carrot_Price-L12 | N12: =SUM($M$5:M12) | O12: =AND(O11,M12>=0) | P12: =ROW()-4 | Q12: =(P12*Mesclun_Base_Labor_Hrs_Wk_Bed*Season_Weeks*(1+Mesclun_Diminishing_Rate)^P12)-((P12-1)*Mesclun_Base_Labor_Hrs_Wk_Bed*Season_Weeks*(1+Mesclun_Diminishing_Rate)^(P12-1)) | R12: =SUM($Q$5:Q12) | S12: =MAX(0,MIN(R12,Own_Labor_Hours)-MIN((R12-Q12),Own_Labor_Hours))*Farmer_Implied_Wage+(Q12-MAX(0,MIN(R12,Own_Labor_Hours)-MIN((R12-Q12),Own_Labor_Hours)))*Temp_Wage_Per_Hour+Mesclun_Fertilizer_Per_Bed | T12: =Mesclun_Price-S12 | U12: =SUM($T$5:T12) | V12: =AND(V11,T12>=0)
B13: =ROW()-4 | C13: =(B13*Tomato_Base_Labor_Hrs_Wk_Bed*Season_Weeks*(1+Tomato_Diminishing_Rate)^B13)-((B13-1)*Tomato_Base_Labor_Hrs_Wk_Bed*Season_Weeks*(1+Tomato_Diminishing_Rate)^(B13-1)) | D13: =SUM($C$5:C13) | E13: =MAX(0,MIN(D13,Own_Labor_Hours)-MIN((D13-C13),Own_Labor_Hours))*Farmer_Implied_Wage+(C13-MAX(0,MIN(D13,Own_Labor_Hours)-MIN((D13-C13),Own_Labor_Hours)))*Temp_Wage_Per_Hour+Tomato_Fertilizer_Per_Bed | F13: =Tomato_Price-E13 | G13: =SUM($F$5:F13) | H13: =AND(H12,F13>=0) | I13: =ROW()-4 | J13: =(I13*Carrot_Base_Labor_Hrs_Wk_Bed*Season_Weeks*(1+Carrot_Diminishing_Rate)^I13)-((I13-1)*Carrot_Base_Labor_Hrs_Wk_Bed*Season_Weeks*(1+Carrot_Diminishing_Rate)^(I13-1)) | K13: =SUM($J$5:J13) | L13: =MAX(0,MIN(K13,Own_Labor_Hours)-MIN((K13-J13),Own_Labor_Hours))*Farmer_Implied_Wage+(J13-MAX(0,MIN(K13,Own_Labor_Hours)-MIN((K13-J13),Own_Labor_Hours)))*Temp_Wage_Per_Hour+Carrot_Fertilizer_Per_Bed | M13: =Carrot_Price-L13 | N13: =SUM($M$5:M13) | O13: =AND(O12,M13>=0) | P13: =ROW()-4 | Q13: =(P13*Mesclun_Base_Labor_Hrs_Wk_Bed*Season_Weeks*(1+Mesclun_Diminishing_Rate)^P13)-((P13-1)*Mesclun_Base_Labor_Hrs_Wk_Bed*Season_Weeks*(1+Mesclun_Diminishing_Rate)^(P13-1)) | R13: =SUM($Q$5:Q13) | S13: =MAX(0,MIN(R13,Own_Labor_Hours)-MIN((R13-Q13),Own_Labor_Hours))*Farmer_Implied_Wage+(Q13-MAX(0,MIN(R13,Own_Labor_Hours)-MIN((R13-Q13),Own_Labor_Hours)))*Temp_Wage_Per_Hour+Mesclun_Fertilizer_Per_Bed | T13: =Mesclun_Price-S13 | U13: =SUM($T$5:T13) | V13: =AND(V12,T13>=0)
B14: =ROW()-4 | C14: =(B14*Tomato_Base_Labor_Hrs_Wk_Bed*Season_Weeks*(1+Tomato_Diminishing_Rate)^B14)-((B14-1)*Tomato_Base_Labor_Hrs_Wk_Bed*Season_Weeks*(1+Tomato_Diminishing_Rate)^(B14-1)) | D14: =SUM($C$5:C14) | E14: =MAX(0,MIN(D14,Own_Labor_Hours)-MIN((D14-C14),Own_Labor_Hours))*Farmer_Implied_Wage+(C14-MAX(0,MIN(D14,Own_Labor_Hours)-MIN((D14-C14),Own_Labor_Hours)))*Temp_Wage_Per_Hour+Tomato_Fertilizer_Per_Bed | F14: =Tomato_Price-E14 | G14: =SUM($F$5:F14) | H14: =AND(H13,F14>=0) | I14: =ROW()-4 | J14: =(I14*Carrot_Base_Labor_Hrs_Wk_Bed*Season_Weeks*(1+Carrot_Diminishing_Rate)^I14)-((I14-1)*Carrot_Base_Labor_Hrs_Wk_Bed*Season_Weeks*(1+Carrot_Diminishing_Rate)^(I14-1)) | K14: =SUM($J$5:J14) | L14: =MAX(0,MIN(K14,Own_Labor_Hours)-MIN((K14-J14),Own_Labor_Hours))*Farmer_Implied_Wage+(J14-MAX(0,MIN(K14,Own_Labor_Hours)-MIN((K14-J14),Own_Labor_Hours)))*Temp_Wage_Per_Hour+Carrot_Fertilizer_Per_Bed | M14: =Carrot_Price-L14 | N14: =SUM($M$5:M14) | O14: =AND(O13,M14>=0) | P14: =ROW()-4 | Q14: =(P14*Mesclun_Base_Labor_Hrs_Wk_Bed*Season_Weeks*(1+Mesclun_Diminishing_Rate)^P14)-((P14-1)*Mesclun_Base_Labor_Hrs_Wk_Bed*Season_Weeks*(1+Mesclun_Diminishing_Rate)^(P14-1)) | R14: =SUM($Q$5:Q14) | S14: =MAX(0,MIN(R14,Own_Labor_Hours)-MIN((R14-Q14),Own_Labor_Hours))*Farmer_Implied_Wage+(Q14-MAX(0,MIN(R14,Own_Labor_Hours)-MIN((R14-Q14),Own_Labor_Hours)))*Temp_Wage_Per_Hour+Mesclun_Fertilizer_Per_Bed | T14: =Mesclun_Price-S14 | U14: =SUM($T$5:T14) | V14: =AND(V13,T14>=0)
B15: =ROW()-4 | C15: =(B15*Tomato_Base_Labor_Hrs_Wk_Bed*Season_Weeks*(1+Tomato_Diminishing_Rate)^B15)-((B15-1)*Tomato_Base_Labor_Hrs_Wk_Bed*Season_Weeks*(1+Tomato_Diminishing_Rate)^(B15-1)) | D15: =SUM($C$5:C15) | E15: =MAX(0,MIN(D15,Own_Labor_Hours)-MIN((D15-C15),Own_Labor_Hours))*Farmer_Implied_Wage+(C15-MAX(0,MIN(D15,Own_Labor_Hours)-MIN((D15-C15),Own_Labor_Hours)))*Temp_Wage_Per_Hour+Tomato_Fertilizer_Per_Bed | F15: =Tomato_Price-E15 | G15: =SUM($F$5:F15) | H15: =AND(H14,F15>=0) | I15: =ROW()-4 | J15: =(I15*Carrot_Base_Labor_Hrs_Wk_Bed*Season_Weeks*(1+Carrot_Diminishing_Rate)^I15)-((I15-1)*Carrot_Base_Labor_Hrs_Wk_Bed*Season_Weeks*(1+Carrot_Diminishing_Rate)^(I15-1)) | K15: =SUM($J$5:J15) | L15: =MAX(0,MIN(K15,Own_Labor_Hours)-MIN((K15-J15),Own_Labor_Hours))*Farmer_Implied_Wage+(J15-MAX(0,MIN(K15,Own_Labor_Hours)-MIN((K15-J15),Own_Labor_Hours)))*Temp_Wage_Per_Hour+Carrot_Fertilizer_Per_Bed | M15: =Carrot_Price-L15 | N15: =SUM($M$5:M15) | O15: =AND(O14,M15>=0) | P15: =ROW()-4 | Q15: =(P15*Mesclun_Base_Labor_Hrs_Wk_Bed*Season_Weeks*(1+Mesclun_Diminishing_Rate)^P15)-((P15-1)*Mesclun_Base_Labor_Hrs_Wk_Bed*Season_Weeks*(1+Mesclun_Diminishing_Rate)^(P15-1)) | R15: =SUM($Q$5:Q15) | S15: =MAX(0,MIN(R15,Own_Labor_Hours)-MIN((R15-Q15),Own_Labor_Hours))*Farmer_Implied_Wage+(Q15-MAX(0,MIN(R15,Own_Labor_Hours)-MIN((R15-Q15),Own_Labor_Hours)))*Temp_Wage_Per_Hour+Mesclun_Fertilizer_Per_Bed | T15: =Mesclun_Price-S15 | U15: =SUM($T$5:T15) | V15: =AND(V14,T15>=0)
B16: =ROW()-4 | C16: =(B16*Tomato_Base_Labor_Hrs_Wk_Bed*Season_Weeks*(1+Tomato_Diminishing_Rate)^B16)-((B16-1)*Tomato_Base_Labor_Hrs_Wk_Bed*Season_Weeks*(1+Tomato_Diminishing_Rate)^(B16-1)) | D16: =SUM($C$5:C16) | E16: =MAX(0,MIN(D16,Own_Labor_Hours)-MIN((D16-C16),Own_Labor_Hours))*Farmer_Implied_Wage+(C16-MAX(0,MIN(D16,Own_Labor_Hours)-MIN((D16-C16),Own_Labor_Hours)))*Temp_Wage_Per_Hour+Tomato_Fertilizer_Per_Bed | F16: =Tomato_Price-E16 | G16: =SUM($F$5:F16) | H16: =AND(H15,F16>=0) | I16: =ROW()-4 | J16: =(I16*Carrot_Base_Labor_Hrs_Wk_Bed*Season_Weeks*(1+Carrot_Diminishing_Rate)^I16)-((I16-1)*Carrot_Base_Labor_Hrs_Wk_Bed*Season_Weeks*(1+Carrot_Diminishing_Rate)^(I16-1)) | K16: =SUM($J$5:J16) | L16: =MAX(0,MIN(K16,Own_Labor_Hours)-MIN((K16-J16),Own_Labor_Hours))*Farmer_Implied_Wage+(J16-MAX(0,MIN(K16,Own_Labor_Hours)-MIN((K16-J16),Own_Labor_Hours)))*Temp_Wage_Per_Hour+Carrot_Fertilizer_Per_Bed | M16: =Carrot_Price-L16 | N16: =SUM($M$5:M16) | O16: =AND(O15,M16>=0) | P16: =ROW()-4 | Q16: =(P16*Mesclun_Base_Labor_Hrs_Wk_Bed*Season_Weeks*(1+Mesclun_Diminishing_Rate)^P16)-((P16-1)*Mesclun_Base_Labor_Hrs_Wk_Bed*Season_Weeks*(1+Mesclun_Diminishing_Rate)^(P16-1)) | R16: =SUM($Q$5:Q16) | S16: =MAX(0,MIN(R16,Own_Labor_Hours)-MIN((R16-Q16),Own_Labor_Hours))*Farmer_Implied_Wage+(Q16-MAX(0,MIN(R16,Own_Labor_Hours)-MIN((R16-Q16),Own_Labor_Hours)))*Temp_Wage_Per_Hour+Mesclun_Fertilizer_Per_Bed | T16: =Mesclun_Price-S16 | U16: =SUM($T$5:T16) | V16: =AND(V15,T16>=0)
B17: =ROW()-4 | C17: =(B17*Tomato_Base_Labor_Hrs_Wk_Bed*Season_Weeks*(1+Tomato_Diminishing_Rate)^B17)-((B17-1)*Tomato_Base_Labor_Hrs_Wk_Bed*Season_Weeks*(1+Tomato_Diminishing_Rate)^(B17-1)) | D17: =SUM($C$5:C17) | E17: =MAX(0,MIN(D17,Own_Labor_Hours)-MIN((D17-C17),Own_Labor_Hours))*Farmer_Implied_Wage+(C17-MAX(0,MIN(D17,Own_Labor_Hours)-MIN((D17-C17),Own_Labor_Hours)))*Temp_Wage_Per_Hour+Tomato_Fertilizer_Per_Bed | F17: =Tomato_Price-E17 | G17: =SUM($F$5:F17) | H17: =AND(H16,F17>=0) | I17: =ROW()-4 | J17: =(I17*Carrot_Base_Labor_Hrs_Wk_Bed*Season_Weeks*(1+Carrot_Diminishing_Rate)^I17)-((I17-1)*Carrot_Base_Labor_Hrs_Wk_Bed*Season_Weeks*(1+Carrot_Diminishing_Rate)^(I17-1)) | K17: =SUM($J$5:J17) | L17: =MAX(0,MIN(K17,Own_Labor_Hours)-MIN((K17-J17),Own_Labor_Hours))*Farmer_Implied_Wage+(J17-MAX(0,MIN(K17,Own_Labor_Hours)-MIN((K17-J17),Own_Labor_Hours)))*Temp_Wage_Per_Hour+Carrot_Fertilizer_Per_Bed | M17: =Carrot_Price-L17 | N17: =SUM($M$5:M17) | O17: =AND(O16,M17>=0) | P17: =ROW()-4 | Q17: =(P17*Mesclun_Base_Labor_Hrs_Wk_Bed*Season_Weeks*(1+Mesclun_Diminishing_Rate)^P17)-((P17-1)*Mesclun_Base_Labor_Hrs_Wk_Bed*Season_Weeks*(1+Mesclun_Diminishing_Rate)^(P17-1)) | R17: =SUM($Q$5:Q17) | S17: =MAX(0,MIN(R17,Own_Labor_Hours)-MIN((R17-Q17),Own_Labor_Hours))*Farmer_Implied_Wage+(Q17-MAX(0,MIN(R17,Own_Labor_Hours)-MIN((R17-Q17),Own_Labor_Hours)))*Temp_Wage_Per_Hour+Mesclun_Fertilizer_Per_Bed | T17: =Mesclun_Price-S17 | U17: =SUM($T$5:T17) | V17: =AND(V16,T17>=0)
... B24: =ROW()-4 | C24: =(B24*Tomato_Base_Labor_Hrs_Wk_Bed*Season_Weeks*(1+Tomato_Diminishing_Rate)^B24)-((B24-1)*Tomato_Base_Labor_Hrs_Wk_Bed*Season_Weeks*(1+Tomato_Diminishing_Rate)^(B24-1)) | D24: =SUM($C$5:C24) | E24: =MAX(0,MIN(D24,Own_Labor_Hours)-MIN((D24-C24),Own_Labor_Hours))*Farmer_Implied_Wage+(C24-MAX(0,MIN(D24,Own_Labor_Hours)-MIN((D24-C24),Own_Labor_Hours)))*Temp_Wage_Per_Hour+Tomato_Fertilizer_Per_Bed | F24: =Tomato_Price-E24 | G24: =SUM($F$5:F24) | H24: =AND(H23,F24>=0) | I24: =ROW()-4 | J24: =(I24*Carrot_Base_Labor_Hrs_Wk_Bed*Season_Weeks*(1+Carrot_Diminishing_Rate)^I24)-((I24-1)*Carrot_Base_Labor_Hrs_Wk_Bed*Season_Weeks*(1+Carrot_Diminishing_Rate)^(I24-1)) | K24: =SUM($J$5:J24) | L24: =MAX(0,MIN(K24,Own_Labor_Hours)-MIN((K24-J24),Own_Labor_Hours))*Farmer_Implied_Wage+(J24-MAX(0,MIN(K24,Own_Labor_Hours)-MIN((K24-J24),Own_Labor_Hours)))*Temp_Wage_Per_Hour+Carrot_Fertilizer_Per_Bed | M24: =Carrot_Price-L24 | N24: =SUM($M$5:M24) | O24: =AND(O23,M24>=0) | P24: =ROW()-4 | Q24: =(P24*Mesclun_Base_Labor_Hrs_Wk_Bed*Season_Weeks*(1+Mesclun_Diminishing_Rate)^P24)-((P24-1)*Mesclun_Base_Labor_Hrs_Wk_Bed*Season_Weeks*(1+Mesclun_Diminishing_Rate)^(P24-1)) | R24: =SUM($Q$5:Q24) | S24: =MAX(0,MIN(R24,Own_Labor_Hours)-MIN((R24-Q24),Own_Labor_Hours))*Farmer_Implied_Wage+(Q24-MAX(0,MIN(R24,Own_Labor_Hours)-MIN((R24-Q24),Own_Labor_Hours)))*Temp_Wage_Per_Hour+Mesclun_Fertilizer_Per_Bed | T24: =Mesclun_Price-S24 | U24: =SUM($T$5:T24) | V24: =AND(V23,T24>=0)
P25: =ROW()-4 | Q25: =(P25*Mesclun_Base_Labor_Hrs_Wk_Bed*Season_Weeks*(1+Mesclun_Diminishing_Rate)^P25)-((P25-1)*Mesclun_Base_Labor_Hrs_Wk_Bed*Season_Weeks*(1+Mesclun_Diminishing_Rate)^(P25-1)) | R25: =SUM($Q$5:Q25) | S25: =MAX(0,MIN(R25,Own_Labor_Hours)-MIN((R25-Q25),Own_Labor_Hours))*Farmer_Implied_Wage+(Q25-MAX(0,MIN(R25,Own_Labor_Hours)-MIN((R25-Q25),Own_Labor_Hours)))*Temp_Wage_Per_Hour+Mesclun_Fertilizer_Per_Bed | T25: =Mesclun_Price-S25 | U25: =SUM($T$5:T25) | V25: =AND(V24,T25>=0)
B26: Standalone last-profitable bed (first crossover, per the lab's own definition): | F26: =SUMPRODUCT((H5:H24)*1) | I26: Standalone last-profitable bed (first crossover, per the lab's own definition): | M26: =SUMPRODUCT((O5:O24)*1) | P26: =ROW()-4 | Q26: =(P26*Mesclun_Base_Labor_Hrs_Wk_Bed*Season_Weeks*(1+Mesclun_Diminishing_Rate)^P26)-((P26-1)*Mesclun_Base_Labor_Hrs_Wk_Bed*Season_Weeks*(1+Mesclun_Diminishing_Rate)^(P26-1)) | R26: =SUM($Q$5:Q26) | S26: =MAX(0,MIN(R26,Own_Labor_Hours)-MIN((R26-Q26),Own_Labor_Hours))*Farmer_Implied_Wage+(Q26-MAX(0,MIN(R26,Own_Labor_Hours)-MIN((R26-Q26),Own_Labor_Hours)))*Temp_Wage_Per_Hour+Mesclun_Fertilizer_Per_Bed | T26: =Mesclun_Price-S26 | U26: =SUM($T$5:T26) | V26: =AND(V25,T26>=0)
P27: =ROW()-4 | Q27: =(P27*Mesclun_Base_Labor_Hrs_Wk_Bed*Season_Weeks*(1+Mesclun_Diminishing_Rate)^P27)-((P27-1)*Mesclun_Base_Labor_Hrs_Wk_Bed*Season_Weeks*(1+Mesclun_Diminishing_Rate)^(P27-1)) | R27: =SUM($Q$5:Q27) | S27: =MAX(0,MIN(R27,Own_Labor_Hours)-MIN((R27-Q27),Own_Labor_Hours))*Farmer_Implied_Wage+(Q27-MAX(0,MIN(R27,Own_Labor_Hours)-MIN((R27-Q27),Own_Labor_Hours)))*Temp_Wage_Per_Hour+Mesclun_Fertilizer_Per_Bed | T27: =Mesclun_Price-S27 | U27: =SUM($T$5:T27) | V27: =AND(V26,T27>=0)
P28: =ROW()-4 | Q28: =(P28*Mesclun_Base_Labor_Hrs_Wk_Bed*Season_Weeks*(1+Mesclun_Diminishing_Rate)^P28)-((P28-1)*Mesclun_Base_Labor_Hrs_Wk_Bed*Season_Weeks*(1+Mesclun_Diminishing_Rate)^(P28-1)) | R28: =SUM($Q$5:Q28) | S28: =MAX(0,MIN(R28,Own_Labor_Hours)-MIN((R28-Q28),Own_Labor_Hours))*Farmer_Implied_Wage+(Q28-MAX(0,MIN(R28,Own_Labor_Hours)-MIN((R28-Q28),Own_Labor_Hours)))*Temp_Wage_Per_Hour+Mesclun_Fertilizer_Per_Bed | T28: =Mesclun_Price-S28 | U28: =SUM($T$5:T28) | V28: =AND(V27,T28>=0)
P29: =ROW()-4 | Q29: =(P29*Mesclun_Base_Labor_Hrs_Wk_Bed*Season_Weeks*(1+Mesclun_Diminishing_Rate)^P29)-((P29-1)*Mesclun_Base_Labor_Hrs_Wk_Bed*Season_Weeks*(1+Mesclun_Diminishing_Rate)^(P29-1)) | R29: =SUM($Q$5:Q29) | S29: =MAX(0,MIN(R29,Own_Labor_Hours)-MIN((R29-Q29),Own_Labor_Hours))*Farmer_Implied_Wage+(Q29-MAX(0,MIN(R29,Own_Labor_Hours)-MIN((R29-Q29),Own_Labor_Hours)))*Temp_Wage_Per_Hour+Mesclun_Fertilizer_Per_Bed | T29: =Mesclun_Price-S29 | U29: =SUM($T$5:T29) | V29: =AND(V28,T29>=0)
P30: =ROW()-4 | Q30: =(P30*Mesclun_Base_Labor_Hrs_Wk_Bed*Season_Weeks*(1+Mesclun_Diminishing_Rate)^P30)-((P30-1)*Mesclun_Base_Labor_Hrs_Wk_Bed*Season_Weeks*(1+Mesclun_Diminishing_Rate)^(P30-1)) | R30: =SUM($Q$5:Q30) | S30: =MAX(0,MIN(R30,Own_Labor_Hours)-MIN((R30-Q30),Own_Labor_Hours))*Farmer_Implied_Wage+(Q30-MAX(0,MIN(R30,Own_Labor_Hours)-MIN((R30-Q30),Own_Labor_Hours)))*Temp_Wage_Per_Hour+Mesclun_Fertilizer_Per_Bed | T30: =Mesclun_Price-S30 | U30: =SUM($T$5:T30) | V30: =AND(V29,T30>=0)
P31: =ROW()-4 | Q31: =(P31*Mesclun_Base_Labor_Hrs_Wk_Bed*Season_Weeks*(1+Mesclun_Diminishing_Rate)^P31)-((P31-1)*Mesclun_Base_Labor_Hrs_Wk_Bed*Season_Weeks*(1+Mesclun_Diminishing_Rate)^(P31-1)) | R31: =SUM($Q$5:Q31) | S31: =MAX(0,MIN(R31,Own_Labor_Hours)-MIN((R31-Q31),Own_Labor_Hours))*Farmer_Implied_Wage+(Q31-MAX(0,MIN(R31,Own_Labor_Hours)-MIN((R31-Q31),Own_Labor_Hours)))*Temp_Wage_Per_Hour+Mesclun_Fertilizer_Per_Bed | T31: =Mesclun_Price-S31 | U31: =SUM($T$5:T31) | V31: =AND(V30,T31>=0)
P32: =ROW()-4 | Q32: =(P32*Mesclun_Base_Labor_Hrs_Wk_Bed*Season_Weeks*(1+Mesclun_Diminishing_Rate)^P32)-((P32-1)*Mesclun_Base_Labor_Hrs_Wk_Bed*Season_Weeks*(1+Mesclun_Diminishing_Rate)^(P32-1)) | R32: =SUM($Q$5:Q32) | S32: =MAX(0,MIN(R32,Own_Labor_Hours)-MIN((R32-Q32),Own_Labor_Hours))*Farmer_Implied_Wage+(Q32-MAX(0,MIN(R32,Own_Labor_Hours)-MIN((R32-Q32),Own_Labor_Hours)))*Temp_Wage_Per_Hour+Mesclun_Fertilizer_Per_Bed | T32: =Mesclun_Price-S32 | U32: =SUM($T$5:T32) | V32: =AND(V31,T32>=0)
P33: =ROW()-4 | Q33: =(P33*Mesclun_Base_Labor_Hrs_Wk_Bed*Season_Weeks*(1+Mesclun_Diminishing_Rate)^P33)-((P33-1)*Mesclun_Base_Labor_Hrs_Wk_Bed*Season_Weeks*(1+Mesclun_Diminishing_Rate)^(P33-1)) | R33: =SUM($Q$5:Q33) | S33: =MAX(0,MIN(R33,Own_Labor_Hours)-MIN((R33-Q33),Own_Labor_Hours))*Farmer_Implied_Wage+(Q33-MAX(0,MIN(R33,Own_Labor_Hours)-MIN((R33-Q33),Own_Labor_Hours)))*Temp_Wage_Per_Hour+Mesclun_Fertilizer_Per_Bed | T33: =Mesclun_Price-S33 | U33: =SUM($T$5:T33) | V33: =AND(V32,T33>=0)
P34: =ROW()-4 | Q34: =(P34*Mesclun_Base_Labor_Hrs_Wk_Bed*Season_Weeks*(1+Mesclun_Diminishing_Rate)^P34)-((P34-1)*Mesclun_Base_Labor_Hrs_Wk_Bed*Season_Weeks*(1+Mesclun_Diminishing_Rate)^(P34-1)) | R34: =SUM($Q$5:Q34) | S34: =MAX(0,MIN(R34,Own_Labor_Hours)-MIN((R34-Q34),Own_Labor_Hours))*Farmer_Implied_Wage+(Q34-MAX(0,MIN(R34,Own_Labor_Hours)-MIN((R34-Q34),Own_Labor_Hours)))*Temp_Wage_Per_Hour+Mesclun_Fertilizer_Per_Bed | T34: =Mesclun_Price-S34 | U34: =SUM($T$5:T34) | V34: =AND(V33,T34>=0)
P36: Standalone last-profitable bed (first crossover, per the lab's own definition): | T36: =SUMPRODUCT((V5:V34)*1)
A38: Joint Allocation (decision cells live on the Solver tab)
A39: Beds — Tomato (from Solver) | E39: =Solver!$C$6
A40: Beds — Carrot (from Solver) | E40: =Solver!$C$7
A41: Beds — Mesclun (from Solver) | E41: =Solver!$C$8
A42: Temp workers hired (from Solver) | E42: =Solver!$C$9
A43: Cumulative labor hrs — Tomato @ chosen beds | E43: =IF($E$39=0,0,INDEX(D5:D24,$E$39))
A44: Cumulative labor hrs — Carrot @ chosen beds | E44: =IF($E$40=0,0,INDEX(K5:K24,$E$40))
A45: Cumulative labor hrs — Mesclun @ chosen beds | E45: =IF($E$41=0,0,INDEX(R5:R34,$E$41))
A46: Total labor hours needed | E46: =$E$43+$E$44+$E$45
A47: Temp workers needed (feasibility count, not a cost) | E47: =MIN(Temp_Worker_Max,IF($E$46<=Own_Labor_Hours,0,CEILING(($E$46-Own_Labor_Hours)/Temp_Worker_Hours,1)))
A48: Temp workers needed, unrounded (spec sec 6 check figure: ~3.16) | E48: =MAX(0,$E$46-Own_Labor_Hours)/Temp_Worker_Hours
A49: Labor cost (tiered: 720 hrs @ Farmer_Implied_Wage, rest @ Temp_Wage_Per_Hour) | E49: =MIN($E$46,Own_Labor_Hours)*Farmer_Implied_Wage+MAX(0,$E$46-Own_Labor_Hours)*Temp_Wage_Per_Hour
A50: Revenue | E50: =$E$39*Tomato_Price+$E$40*Carrot_Price+$E$41*Mesclun_Price
A51: Fertilizer cost | E51: =$E$39*Tomato_Fertilizer_Per_Bed+$E$40*Carrot_Fertilizer_Per_Bed+$E$41*Mesclun_Fertilizer_Per_Bed
A52: Total Contribution (before fixed cost) | E52: =$E$50-$E$51-$E$49
A53: PROFIT (after Fixed_Cost) | E53: =$E$52-Fixed_Cost
A55: Validation Checks
A56: Tomato beds <= cap | E56: =IF($E$39<=Tomato_Bed_Cap,"OK","VIOLATION")
A57: Carrot beds <= cap | E57: =IF($E$40<=Carrot_Bed_Cap,"OK","VIOLATION")
A58: Mesclun beds <= cap | E58: =IF($E$41<=Mesclun_Bed_Cap,"OK","VIOLATION")
A59: Total beds <= Total_Beds | E59: =IF($E$39+$E$40+$E$41<=Total_Beds,"OK","VIOLATION")
A60: Temp workers integer, 0 <= n <= Temp_Worker_Max | E60: =IF(AND($E$42=INT($E$42),$E$42>=0,$E$42<=Temp_Worker_Max),"OK","VIOLATION")
A61: Labor hours covered by own + hired capacity | E61: =IF($E$46<=Own_Labor_Hours+$E$42*Temp_Worker_Hours,"OK","VIOLATION - hire more workers")
A62: Temp_Workers_Hired (Solver) >= workers actually needed | E62: =IF($E$42>=$E$47,"OK","VIOLATION - under-hired")
A65: Hypothesis Checks (spec §7)
A66: Check 1 — Carrots > Mesclun beds? (mesclun's edge fails if TRUE) | E66: =IF($E$40>$E$41,"FAILS - carrots > mesclun","holds")
A68: Check 5 — Swap test: Mesclun -1 bed, Carrot +1 bed
A69: Cumulative hrs — Carrot @ swapped beds (N/A if carrot's already at its cap) | E69: =IF(($E$40+1)>Carrot_Bed_Cap,"N/A",IF(($E$40+1)=0,0,INDEX(K5:K24,($E$40+1))))
A70: Cumulative hrs — Mesclun @ swapped beds | E70: =IF(($E$41-1)<=0,0,INDEX(R5:R34,($E$41-1)))
A71: Total labor hours needed (swapped) | E71: =IF(ISTEXT(E69),"N/A",$E$43+E69+E70)
A72: Labor cost (swapped) | E72: =IF(ISTEXT(E71),"N/A",MIN(E71,Own_Labor_Hours)*Farmer_Implied_Wage+MAX(0,E71-Own_Labor_Hours)*Temp_Wage_Per_Hour)
A73: Total Contribution (swapped, before fixed cost) | E73: =IF(ISTEXT(E72),"N/A",$E$39*Tomato_Price+($E$40+1)*Carrot_Price+($E$41-1)*Mesclun_Price-($E$39*Tomato_Fertilizer_Per_Bed+($E$40+1)*Carrot_Fertilizer_Per_Bed+($E$41-1)*Mesclun_Fertilizer_Per_Bed)-E72)
A74: Delta vs. current allocation | E74: =IF(ISTEXT(E73),"N/A",E73-$E$52)
A75: Verdict | E75: =IF(ISTEXT(E74),"N/A - carrot is already at its bed cap, can't add a bed there",IF(E74>0,"FAILS - swap raises contribution, mesclun overconcentrated","holds - current mix is locally optimal for this swap"))
A78: Greedy P = MC Walk (spec §5) — allocate each next bed to whichever crop has the highest marginal profit right now
A79: Stops when either 64 beds are filled or no crop's next bed has positive marginal profit, whichever first.
A81: Step | B81: Chosen crop | C81: Beds Tomato | D81: Beds Carrot | E81: Beds Mesclun | F81: Cum. Hrs (shared) | G81: Cand. profit — Tomato | H81: Cand. profit — Carrot | I81: Cand. profit — Mesclun
A82: 1 | B82: =IF(NOT(AND(MAX(G82,H82,I82)>0,0+0+0<Total_Beds)),"(stopped)",IF(G82=MAX(G82,H82,I82),"Tomato",IF(H82=MAX(G82,H82,I82),"Carrot","Mesclun"))) | C82: =0+IF(B82="Tomato",1,0) | D82: =0+IF(B82="Carrot",1,0) | E82: =0+IF(B82="Mesclun",1,0) | F82: =0+IF(B82="Tomato",INDEX(C5:C24,0+1),IF(B82="Carrot",INDEX(J5:J24,0+1),IF(B82="Mesclun",INDEX(Q5:Q34,0+1),0))) | G82: =IF(0<Tomato_Bed_Cap,Tomato_Price-(MAX(0,MIN(0+INDEX(C5:C24,0+1),Own_Labor_Hours)-MIN(0,Own_Labor_Hours))*Farmer_Implied_Wage+(INDEX(C5:C24,0+1)-MAX(0,MIN(0+INDEX(C5:C24,0+1),Own_Labor_Hours)-MIN(0,Own_Labor_Hours)))*Temp_Wage_Per_Hour+Tomato_Fertilizer_Per_Bed),-1E+018) | H82: =IF(0<Carrot_Bed_Cap,Carrot_Price-(MAX(0,MIN(0+INDEX(J5:J24,0+1),Own_Labor_Hours)-MIN(0,Own_Labor_Hours))*Farmer_Implied_Wage+(INDEX(J5:J24,0+1)-MAX(0,MIN(0+INDEX(J5:J24,0+1),Own_Labor_Hours)-MIN(0,Own_Labor_Hours)))*Temp_Wage_Per_Hour+Carrot_Fertilizer_Per_Bed),-1E+018) | I82: =IF(0<Mesclun_Bed_Cap,Mesclun_Price-(MAX(0,MIN(0+INDEX(Q5:Q34,0+1),Own_Labor_Hours)-MIN(0,Own_Labor_Hours))*Farmer_Implied_Wage+(INDEX(Q5:Q34,0+1)-MAX(0,MIN(0+INDEX(Q5:Q34,0+1),Own_Labor_Hours)-MIN(0,Own_Labor_Hours)))*Temp_Wage_Per_Hour+Mesclun_Fertilizer_Per_Bed),-1E+018)
A83: 2 | B83: =IF(NOT(AND(MAX(G83,H83,I83)>0,C82+D82+E82<Total_Beds)),"(stopped)",IF(G83=MAX(G83,H83,I83),"Tomato",IF(H83=MAX(G83,H83,I83),"Carrot","Mesclun"))) | C83: =C82+IF(B83="Tomato",1,0) | D83: =D82+IF(B83="Carrot",1,0) | E83: =E82+IF(B83="Mesclun",1,0) | F83: =F82+IF(B83="Tomato",INDEX(C5:C24,C82+1),IF(B83="Carrot",INDEX(J5:J24,D82+1),IF(B83="Mesclun",INDEX(Q5:Q34,E82+1),0))) | G83: =IF(C82<Tomato_Bed_Cap,Tomato_Price-(MAX(0,MIN(F82+INDEX(C5:C24,C82+1),Own_Labor_Hours)-MIN(F82,Own_Labor_Hours))*Farmer_Implied_Wage+(INDEX(C5:C24,C82+1)-MAX(0,MIN(F82+INDEX(C5:C24,C82+1),Own_Labor_Hours)-MIN(F82,Own_Labor_Hours)))*Temp_Wage_Per_Hour+Tomato_Fertilizer_Per_Bed),-1E+018) | H83: =IF(D82<Carrot_Bed_Cap,Carrot_Price-(MAX(0,MIN(F82+INDEX(J5:J24,D82+1),Own_Labor_Hours)-MIN(F82,Own_Labor_Hours))*Farmer_Implied_Wage+(INDEX(J5:J24,D82+1)-MAX(0,MIN(F82+INDEX(J5:J24,D82+1),Own_Labor_Hours)-MIN(F82,Own_Labor_Hours)))*Temp_Wage_Per_Hour+Carrot_Fertilizer_Per_Bed),-1E+018) | I83: =IF(E82<Mesclun_Bed_Cap,Mesclun_Price-(MAX(0,MIN(F82+INDEX(Q5:Q34,E82+1),Own_Labor_Hours)-MIN(F82,Own_Labor_Hours))*Farmer_Implied_Wage+(INDEX(Q5:Q34,E82+1)-MAX(0,MIN(F82+INDEX(Q5:Q34,E82+1),Own_Labor_Hours)-MIN(F82,Own_Labor_Hours)))*Temp_Wage_Per_Hour+Mesclun_Fertilizer_Per_Bed),-1E+018)
A84: 3 | B84: =IF(NOT(AND(MAX(G84,H84,I84)>0,C83+D83+E83<Total_Beds)),"(stopped)",IF(G84=MAX(G84,H84,I84),"Tomato",IF(H84=MAX(G84,H84,I84),"Carrot","Mesclun"))) | C84: =C83+IF(B84="Tomato",1,0) | D84: =D83+IF(B84="Carrot",1,0) | E84: =E83+IF(B84="Mesclun",1,0) | F84: =F83+IF(B84="Tomato",INDEX(C5:C24,C83+1),IF(B84="Carrot",INDEX(J5:J24,D83+1),IF(B84="Mesclun",INDEX(Q5:Q34,E83+1),0))) | G84: =IF(C83<Tomato_Bed_Cap,Tomato_Price-(MAX(0,MIN(F83+INDEX(C5:C24,C83+1),Own_Labor_Hours)-MIN(F83,Own_Labor_Hours))*Farmer_Implied_Wage+(INDEX(C5:C24,C83+1)-MAX(0,MIN(F83+INDEX(C5:C24,C83+1),Own_Labor_Hours)-MIN(F83,Own_Labor_Hours)))*Temp_Wage_Per_Hour+Tomato_Fertilizer_Per_Bed),-1E+018) | H84: =IF(D83<Carrot_Bed_Cap,Carrot_Price-(MAX(0,MIN(F83+INDEX(J5:J24,D83+1),Own_Labor_Hours)-MIN(F83,Own_Labor_Hours))*Farmer_Implied_Wage+(INDEX(J5:J24,D83+1)-MAX(0,MIN(F83+INDEX(J5:J24,D83+1),Own_Labor_Hours)-MIN(F83,Own_Labor_Hours)))*Temp_Wage_Per_Hour+Carrot_Fertilizer_Per_Bed),-1E+018) | I84: =IF(E83<Mesclun_Bed_Cap,Mesclun_Price-(MAX(0,MIN(F83+INDEX(Q5:Q34,E83+1),Own_Labor_Hours)-MIN(F83,Own_Labor_Hours))*Farmer_Implied_Wage+(INDEX(Q5:Q34,E83+1)-MAX(0,MIN(F83+INDEX(Q5:Q34,E83+1),Own_Labor_Hours)-MIN(F83,Own_Labor_Hours)))*Temp_Wage_Per_Hour+Mesclun_Fertilizer_Per_Bed),-1E+018)
A85: 4 | B85: =IF(NOT(AND(MAX(G85,H85,I85)>0,C84+D84+E84<Total_Beds)),"(stopped)",IF(G85=MAX(G85,H85,I85),"Tomato",IF(H85=MAX(G85,H85,I85),"Carrot","Mesclun"))) | C85: =C84+IF(B85="Tomato",1,0) | D85: =D84+IF(B85="Carrot",1,0) | E85: =E84+IF(B85="Mesclun",1,0) | F85: =F84+IF(B85="Tomato",INDEX(C5:C24,C84+1),IF(B85="Carrot",INDEX(J5:J24,D84+1),IF(B85="Mesclun",INDEX(Q5:Q34,E84+1),0))) | G85: =IF(C84<Tomato_Bed_Cap,Tomato_Price-(MAX(0,MIN(F84+INDEX(C5:C24,C84+1),Own_Labor_Hours)-MIN(F84,Own_Labor_Hours))*Farmer_Implied_Wage+(INDEX(C5:C24,C84+1)-MAX(0,MIN(F84+INDEX(C5:C24,C84+1),Own_Labor_Hours)-MIN(F84,Own_Labor_Hours)))*Temp_Wage_Per_Hour+Tomato_Fertilizer_Per_Bed),-1E+018) | H85: =IF(D84<Carrot_Bed_Cap,Carrot_Price-(MAX(0,MIN(F84+INDEX(J5:J24,D84+1),Own_Labor_Hours)-MIN(F84,Own_Labor_Hours))*Farmer_Implied_Wage+(INDEX(J5:J24,D84+1)-MAX(0,MIN(F84+INDEX(J5:J24,D84+1),Own_Labor_Hours)-MIN(F84,Own_Labor_Hours)))*Temp_Wage_Per_Hour+Carrot_Fertilizer_Per_Bed),-1E+018) | I85: =IF(E84<Mesclun_Bed_Cap,Mesclun_Price-(MAX(0,MIN(F84+INDEX(Q5:Q34,E84+1),Own_Labor_Hours)-MIN(F84,Own_Labor_Hours))*Farmer_Implied_Wage+(INDEX(Q5:Q34,E84+1)-MAX(0,MIN(F84+INDEX(Q5:Q34,E84+1),Own_Labor_Hours)-MIN(F84,Own_Labor_Hours)))*Temp_Wage_Per_Hour+Mesclun_Fertilizer_Per_Bed),-1E+018)
A86: 5 | B86: =IF(NOT(AND(MAX(G86,H86,I86)>0,C85+D85+E85<Total_Beds)),"(stopped)",IF(G86=MAX(G86,H86,I86),"Tomato",IF(H86=MAX(G86,H86,I86),"Carrot","Mesclun"))) | C86: =C85+IF(B86="Tomato",1,0) | D86: =D85+IF(B86="Carrot",1,0) | E86: =E85+IF(B86="Mesclun",1,0) | F86: =F85+IF(B86="Tomato",INDEX(C5:C24,C85+1),IF(B86="Carrot",INDEX(J5:J24,D85+1),IF(B86="Mesclun",INDEX(Q5:Q34,E85+1),0))) | G86: =IF(C85<Tomato_Bed_Cap,Tomato_Price-(MAX(0,MIN(F85+INDEX(C5:C24,C85+1),Own_Labor_Hours)-MIN(F85,Own_Labor_Hours))*Farmer_Implied_Wage+(INDEX(C5:C24,C85+1)-MAX(0,MIN(F85+INDEX(C5:C24,C85+1),Own_Labor_Hours)-MIN(F85,Own_Labor_Hours)))*Temp_Wage_Per_Hour+Tomato_Fertilizer_Per_Bed),-1E+018) | H86: =IF(D85<Carrot_Bed_Cap,Carrot_Price-(MAX(0,MIN(F85+INDEX(J5:J24,D85+1),Own_Labor_Hours)-MIN(F85,Own_Labor_Hours))*Farmer_Implied_Wage+(INDEX(J5:J24,D85+1)-MAX(0,MIN(F85+INDEX(J5:J24,D85+1),Own_Labor_Hours)-MIN(F85,Own_Labor_Hours)))*Temp_Wage_Per_Hour+Carrot_Fertilizer_Per_Bed),-1E+018) | I86: =IF(E85<Mesclun_Bed_Cap,Mesclun_Price-(MAX(0,MIN(F85+INDEX(Q5:Q34,E85+1),Own_Labor_Hours)-MIN(F85,Own_Labor_Hours))*Farmer_Implied_Wage+(INDEX(Q5:Q34,E85+1)-MAX(0,MIN(F85+INDEX(Q5:Q34,E85+1),Own_Labor_Hours)-MIN(F85,Own_Labor_Hours)))*Temp_Wage_Per_Hour+Mesclun_Fertilizer_Per_Bed),-1E+018)
A87: 6 | B87: =IF(NOT(AND(MAX(G87,H87,I87)>0,C86+D86+E86<Total_Beds)),"(stopped)",IF(G87=MAX(G87,H87,I87),"Tomato",IF(H87=MAX(G87,H87,I87),"Carrot","Mesclun"))) | C87: =C86+IF(B87="Tomato",1,0) | D87: =D86+IF(B87="Carrot",1,0) | E87: =E86+IF(B87="Mesclun",1,0) | F87: =F86+IF(B87="Tomato",INDEX(C5:C24,C86+1),IF(B87="Carrot",INDEX(J5:J24,D86+1),IF(B87="Mesclun",INDEX(Q5:Q34,E86+1),0))) | G87: =IF(C86<Tomato_Bed_Cap,Tomato_Price-(MAX(0,MIN(F86+INDEX(C5:C24,C86+1),Own_Labor_Hours)-MIN(F86,Own_Labor_Hours))*Farmer_Implied_Wage+(INDEX(C5:C24,C86+1)-MAX(0,MIN(F86+INDEX(C5:C24,C86+1),Own_Labor_Hours)-MIN(F86,Own_Labor_Hours)))*Temp_Wage_Per_Hour+Tomato_Fertilizer_Per_Bed),-1E+018) | H87: =IF(D86<Carrot_Bed_Cap,Carrot_Price-(MAX(0,MIN(F86+INDEX(J5:J24,D86+1),Own_Labor_Hours)-MIN(F86,Own_Labor_Hours))*Farmer_Implied_Wage+(INDEX(J5:J24,D86+1)-MAX(0,MIN(F86+INDEX(J5:J24,D86+1),Own_Labor_Hours)-MIN(F86,Own_Labor_Hours)))*Temp_Wage_Per_Hour+Carrot_Fertilizer_Per_Bed),-1E+018) | I87: =IF(E86<Mesclun_Bed_Cap,Mesclun_Price-(MAX(0,MIN(F86+INDEX(Q5:Q34,E86+1),Own_Labor_Hours)-MIN(F86,Own_Labor_Hours))*Farmer_Implied_Wage+(INDEX(Q5:Q34,E86+1)-MAX(0,MIN(F86+INDEX(Q5:Q34,E86+1),Own_Labor_Hours)-MIN(F86,Own_Labor_Hours)))*Temp_Wage_Per_Hour+Mesclun_Fertilizer_Per_Bed),-1E+018)
A88: 7 | B88: =IF(NOT(AND(MAX(G88,H88,I88)>0,C87+D87+E87<Total_Beds)),"(stopped)",IF(G88=MAX(G88,H88,I88),"Tomato",IF(H88=MAX(G88,H88,I88),"Carrot","Mesclun"))) | C88: =C87+IF(B88="Tomato",1,0) | D88: =D87+IF(B88="Carrot",1,0) | E88: =E87+IF(B88="Mesclun",1,0) | F88: =F87+IF(B88="Tomato",INDEX(C5:C24,C87+1),IF(B88="Carrot",INDEX(J5:J24,D87+1),IF(B88="Mesclun",INDEX(Q5:Q34,E87+1),0))) | G88: =IF(C87<Tomato_Bed_Cap,Tomato_Price-(MAX(0,MIN(F87+INDEX(C5:C24,C87+1),Own_Labor_Hours)-MIN(F87,Own_Labor_Hours))*Farmer_Implied_Wage+(INDEX(C5:C24,C87+1)-MAX(0,MIN(F87+INDEX(C5:C24,C87+1),Own_Labor_Hours)-MIN(F87,Own_Labor_Hours)))*Temp_Wage_Per_Hour+Tomato_Fertilizer_Per_Bed),-1E+018) | H88: =IF(D87<Carrot_Bed_Cap,Carrot_Price-(MAX(0,MIN(F87+INDEX(J5:J24,D87+1),Own_Labor_Hours)-MIN(F87,Own_Labor_Hours))*Farmer_Implied_Wage+(INDEX(J5:J24,D87+1)-MAX(0,MIN(F87+INDEX(J5:J24,D87+1),Own_Labor_Hours)-MIN(F87,Own_Labor_Hours)))*Temp_Wage_Per_Hour+Carrot_Fertilizer_Per_Bed),-1E+018) | I88: =IF(E87<Mesclun_Bed_Cap,Mesclun_Price-(MAX(0,MIN(F87+INDEX(Q5:Q34,E87+1),Own_Labor_Hours)-MIN(F87,Own_Labor_Hours))*Farmer_Implied_Wage+(INDEX(Q5:Q34,E87+1)-MAX(0,MIN(F87+INDEX(Q5:Q34,E87+1),Own_Labor_Hours)-MIN(F87,Own_Labor_Hours)))*Temp_Wage_Per_Hour+Mesclun_Fertilizer_Per_Bed),-1E+018)
A89: 8 | B89: =IF(NOT(AND(MAX(G89,H89,I89)>0,C88+D88+E88<Total_Beds)),"(stopped)",IF(G89=MAX(G89,H89,I89),"Tomato",IF(H89=MAX(G89,H89,I89),"Carrot","Mesclun"))) | C89: =C88+IF(B89="Tomato",1,0) | D89: =D88+IF(B89="Carrot",1,0) | E89: =E88+IF(B89="Mesclun",1,0) | F89: =F88+IF(B89="Tomato",INDEX(C5:C24,C88+1),IF(B89="Carrot",INDEX(J5:J24,D88+1),IF(B89="Mesclun",INDEX(Q5:Q34,E88+1),0))) | G89: =IF(C88<Tomato_Bed_Cap,Tomato_Price-(MAX(0,MIN(F88+INDEX(C5:C24,C88+1),Own_Labor_Hours)-MIN(F88,Own_Labor_Hours))*Farmer_Implied_Wage+(INDEX(C5:C24,C88+1)-MAX(0,MIN(F88+INDEX(C5:C24,C88+1),Own_Labor_Hours)-MIN(F88,Own_Labor_Hours)))*Temp_Wage_Per_Hour+Tomato_Fertilizer_Per_Bed),-1E+018) | H89: =IF(D88<Carrot_Bed_Cap,Carrot_Price-(MAX(0,MIN(F88+INDEX(J5:J24,D88+1),Own_Labor_Hours)-MIN(F88,Own_Labor_Hours))*Farmer_Implied_Wage+(INDEX(J5:J24,D88+1)-MAX(0,MIN(F88+INDEX(J5:J24,D88+1),Own_Labor_Hours)-MIN(F88,Own_Labor_Hours)))*Temp_Wage_Per_Hour+Carrot_Fertilizer_Per_Bed),-1E+018) | I89: =IF(E88<Mesclun_Bed_Cap,Mesclun_Price-(MAX(0,MIN(F88+INDEX(Q5:Q34,E88+1),Own_Labor_Hours)-MIN(F88,Own_Labor_Hours))*Farmer_Implied_Wage+(INDEX(Q5:Q34,E88+1)-MAX(0,MIN(F88+INDEX(Q5:Q34,E88+1),Own_Labor_Hours)-MIN(F88,Own_Labor_Hours)))*Temp_Wage_Per_Hour+Mesclun_Fertilizer_Per_Bed),-1E+018)
A90: 9 | B90: =IF(NOT(AND(MAX(G90,H90,I90)>0,C89+D89+E89<Total_Beds)),"(stopped)",IF(G90=MAX(G90,H90,I90),"Tomato",IF(H90=MAX(G90,H90,I90),"Carrot","Mesclun"))) | C90: =C89+IF(B90="Tomato",1,0) | D90: =D89+IF(B90="Carrot",1,0) | E90: =E89+IF(B90="Mesclun",1,0) | F90: =F89+IF(B90="Tomato",INDEX(C5:C24,C89+1),IF(B90="Carrot",INDEX(J5:J24,D89+1),IF(B90="Mesclun",INDEX(Q5:Q34,E89+1),0))) | G90: =IF(C89<Tomato_Bed_Cap,Tomato_Price-(MAX(0,MIN(F89+INDEX(C5:C24,C89+1),Own_Labor_Hours)-MIN(F89,Own_Labor_Hours))*Farmer_Implied_Wage+(INDEX(C5:C24,C89+1)-MAX(0,MIN(F89+INDEX(C5:C24,C89+1),Own_Labor_Hours)-MIN(F89,Own_Labor_Hours)))*Temp_Wage_Per_Hour+Tomato_Fertilizer_Per_Bed),-1E+018) | H90: =IF(D89<Carrot_Bed_Cap,Carrot_Price-(MAX(0,MIN(F89+INDEX(J5:J24,D89+1),Own_Labor_Hours)-MIN(F89,Own_Labor_Hours))*Farmer_Implied_Wage+(INDEX(J5:J24,D89+1)-MAX(0,MIN(F89+INDEX(J5:J24,D89+1),Own_Labor_Hours)-MIN(F89,Own_Labor_Hours)))*Temp_Wage_Per_Hour+Carrot_Fertilizer_Per_Bed),-1E+018) | I90: =IF(E89<Mesclun_Bed_Cap,Mesclun_Price-(MAX(0,MIN(F89+INDEX(Q5:Q34,E89+1),Own_Labor_Hours)-MIN(F89,Own_Labor_Hours))*Farmer_Implied_Wage+(INDEX(Q5:Q34,E89+1)-MAX(0,MIN(F89+INDEX(Q5:Q34,E89+1),Own_Labor_Hours)-MIN(F89,Own_Labor_Hours)))*Temp_Wage_Per_Hour+Mesclun_Fertilizer_Per_Bed),-1E+018)
A91: 10 | B91: =IF(NOT(AND(MAX(G91,H91,I91)>0,C90+D90+E90<Total_Beds)),"(stopped)",IF(G91=MAX(G91,H91,I91),"Tomato",IF(H91=MAX(G91,H91,I91),"Carrot","Mesclun"))) | C91: =C90+IF(B91="Tomato",1,0) | D91: =D90+IF(B91="Carrot",1,0) | E91: =E90+IF(B91="Mesclun",1,0) | F91: =F90+IF(B91="Tomato",INDEX(C5:C24,C90+1),IF(B91="Carrot",INDEX(J5:J24,D90+1),IF(B91="Mesclun",INDEX(Q5:Q34,E90+1),0))) | G91: =IF(C90<Tomato_Bed_Cap,Tomato_Price-(MAX(0,MIN(F90+INDEX(C5:C24,C90+1),Own_Labor_Hours)-MIN(F90,Own_Labor_Hours))*Farmer_Implied_Wage+(INDEX(C5:C24,C90+1)-MAX(0,MIN(F90+INDEX(C5:C24,C90+1),Own_Labor_Hours)-MIN(F90,Own_Labor_Hours)))*Temp_Wage_Per_Hour+Tomato_Fertilizer_Per_Bed),-1E+018) | H91: =IF(D90<Carrot_Bed_Cap,Carrot_Price-(MAX(0,MIN(F90+INDEX(J5:J24,D90+1),Own_Labor_Hours)-MIN(F90,Own_Labor_Hours))*Farmer_Implied_Wage+(INDEX(J5:J24,D90+1)-MAX(0,MIN(F90+INDEX(J5:J24,D90+1),Own_Labor_Hours)-MIN(F90,Own_Labor_Hours)))*Temp_Wage_Per_Hour+Carrot_Fertilizer_Per_Bed),-1E+018) | I91: =IF(E90<Mesclun_Bed_Cap,Mesclun_Price-(MAX(0,MIN(F90+INDEX(Q5:Q34,E90+1),Own_Labor_Hours)-MIN(F90,Own_Labor_Hours))*Farmer_Implied_Wage+(INDEX(Q5:Q34,E90+1)-MAX(0,MIN(F90+INDEX(Q5:Q34,E90+1),Own_Labor_Hours)-MIN(F90,Own_Labor_Hours)))*Temp_Wage_Per_Hour+Mesclun_Fertilizer_Per_Bed),-1E+018)
A92: 11 | B92: =IF(NOT(AND(MAX(G92,H92,I92)>0,C91+D91+E91<Total_Beds)),"(stopped)",IF(G92=MAX(G92,H92,I92),"Tomato",IF(H92=MAX(G92,H92,I92),"Carrot","Mesclun"))) | C92: =C91+IF(B92="Tomato",1,0) | D92: =D91+IF(B92="Carrot",1,0) | E92: =E91+IF(B92="Mesclun",1,0) | F92: =F91+IF(B92="Tomato",INDEX(C5:C24,C91+1),IF(B92="Carrot",INDEX(J5:J24,D91+1),IF(B92="Mesclun",INDEX(Q5:Q34,E91+1),0))) | G92: =IF(C91<Tomato_Bed_Cap,Tomato_Price-(MAX(0,MIN(F91+INDEX(C5:C24,C91+1),Own_Labor_Hours)-MIN(F91,Own_Labor_Hours))*Farmer_Implied_Wage+(INDEX(C5:C24,C91+1)-MAX(0,MIN(F91+INDEX(C5:C24,C91+1),Own_Labor_Hours)-MIN(F91,Own_Labor_Hours)))*Temp_Wage_Per_Hour+Tomato_Fertilizer_Per_Bed),-1E+018) | H92: =IF(D91<Carrot_Bed_Cap,Carrot_Price-(MAX(0,MIN(F91+INDEX(J5:J24,D91+1),Own_Labor_Hours)-MIN(F91,Own_Labor_Hours))*Farmer_Implied_Wage+(INDEX(J5:J24,D91+1)-MAX(0,MIN(F91+INDEX(J5:J24,D91+1),Own_Labor_Hours)-MIN(F91,Own_Labor_Hours)))*Temp_Wage_Per_Hour+Carrot_Fertilizer_Per_Bed),-1E+018) | I92: =IF(E91<Mesclun_Bed_Cap,Mesclun_Price-(MAX(0,MIN(F91+INDEX(Q5:Q34,E91+1),Own_Labor_Hours)-MIN(F91,Own_Labor_Hours))*Farmer_Implied_Wage+(INDEX(Q5:Q34,E91+1)-MAX(0,MIN(F91+INDEX(Q5:Q34,E91+1),Own_Labor_Hours)-MIN(F91,Own_Labor_Hours)))*Temp_Wage_Per_Hour+Mesclun_Fertilizer_Per_Bed),-1E+018)
A93: 12 | B93: =IF(NOT(AND(MAX(G93,H93,I93)>0,C92+D92+E92<Total_Beds)),"(stopped)",IF(G93=MAX(G93,H93,I93),"Tomato",IF(H93=MAX(G93,H93,I93),"Carrot","Mesclun"))) | C93: =C92+IF(B93="Tomato",1,0) | D93: =D92+IF(B93="Carrot",1,0) | E93: =E92+IF(B93="Mesclun",1,0) | F93: =F92+IF(B93="Tomato",INDEX(C5:C24,C92+1),IF(B93="Carrot",INDEX(J5:J24,D92+1),IF(B93="Mesclun",INDEX(Q5:Q34,E92+1),0))) | G93: =IF(C92<Tomato_Bed_Cap,Tomato_Price-(MAX(0,MIN(F92+INDEX(C5:C24,C92+1),Own_Labor_Hours)-MIN(F92,Own_Labor_Hours))*Farmer_Implied_Wage+(INDEX(C5:C24,C92+1)-MAX(0,MIN(F92+INDEX(C5:C24,C92+1),Own_Labor_Hours)-MIN(F92,Own_Labor_Hours)))*Temp_Wage_Per_Hour+Tomato_Fertilizer_Per_Bed),-1E+018) | H93: =IF(D92<Carrot_Bed_Cap,Carrot_Price-(MAX(0,MIN(F92+INDEX(J5:J24,D92+1),Own_Labor_Hours)-MIN(F92,Own_Labor_Hours))*Farmer_Implied_Wage+(INDEX(J5:J24,D92+1)-MAX(0,MIN(F92+INDEX(J5:J24,D92+1),Own_Labor_Hours)-MIN(F92,Own_Labor_Hours)))*Temp_Wage_Per_Hour+Carrot_Fertilizer_Per_Bed),-1E+018) | I93: =IF(E92<Mesclun_Bed_Cap,Mesclun_Price-(MAX(0,MIN(F92+INDEX(Q5:Q34,E92+1),Own_Labor_Hours)-MIN(F92,Own_Labor_Hours))*Farmer_Implied_Wage+(INDEX(Q5:Q34,E92+1)-MAX(0,MIN(F92+INDEX(Q5:Q34,E92+1),Own_Labor_Hours)-MIN(F92,Own_Labor_Hours)))*Temp_Wage_Per_Hour+Mesclun_Fertilizer_Per_Bed),-1E+018)
A94: 13 | B94: =IF(NOT(AND(MAX(G94,H94,I94)>0,C93+D93+E93<Total_Beds)),"(stopped)",IF(G94=MAX(G94,H94,I94),"Tomato",IF(H94=MAX(G94,H94,I94),"Carrot","Mesclun"))) | C94: =C93+IF(B94="Tomato",1,0) | D94: =D93+IF(B94="Carrot",1,0) | E94: =E93+IF(B94="Mesclun",1,0) | F94: =F93+IF(B94="Tomato",INDEX(C5:C24,C93+1),IF(B94="Carrot",INDEX(J5:J24,D93+1),IF(B94="Mesclun",INDEX(Q5:Q34,E93+1),0))) | G94: =IF(C93<Tomato_Bed_Cap,Tomato_Price-(MAX(0,MIN(F93+INDEX(C5:C24,C93+1),Own_Labor_Hours)-MIN(F93,Own_Labor_Hours))*Farmer_Implied_Wage+(INDEX(C5:C24,C93+1)-MAX(0,MIN(F93+INDEX(C5:C24,C93+1),Own_Labor_Hours)-MIN(F93,Own_Labor_Hours)))*Temp_Wage_Per_Hour+Tomato_Fertilizer_Per_Bed),-1E+018) | H94: =IF(D93<Carrot_Bed_Cap,Carrot_Price-(MAX(0,MIN(F93+INDEX(J5:J24,D93+1),Own_Labor_Hours)-MIN(F93,Own_Labor_Hours))*Farmer_Implied_Wage+(INDEX(J5:J24,D93+1)-MAX(0,MIN(F93+INDEX(J5:J24,D93+1),Own_Labor_Hours)-MIN(F93,Own_Labor_Hours)))*Temp_Wage_Per_Hour+Carrot_Fertilizer_Per_Bed),-1E+018) | I94: =IF(E93<Mesclun_Bed_Cap,Mesclun_Price-(MAX(0,MIN(F93+INDEX(Q5:Q34,E93+1),Own_Labor_Hours)-MIN(F93,Own_Labor_Hours))*Farmer_Implied_Wage+(INDEX(Q5:Q34,E93+1)-MAX(0,MIN(F93+INDEX(Q5:Q34,E93+1),Own_Labor_Hours)-MIN(F93,Own_Labor_Hours)))*Temp_Wage_Per_Hour+Mesclun_Fertilizer_Per_Bed),-1E+018)
A95: 14 | B95: =IF(NOT(AND(MAX(G95,H95,I95)>0,C94+D94+E94<Total_Beds)),"(stopped)",IF(G95=MAX(G95,H95,I95),"Tomato",IF(H95=MAX(G95,H95,I95),"Carrot","Mesclun"))) | C95: =C94+IF(B95="Tomato",1,0) | D95: =D94+IF(B95="Carrot",1,0) | E95: =E94+IF(B95="Mesclun",1,0) | F95: =F94+IF(B95="Tomato",INDEX(C5:C24,C94+1),IF(B95="Carrot",INDEX(J5:J24,D94+1),IF(B95="Mesclun",INDEX(Q5:Q34,E94+1),0))) | G95: =IF(C94<Tomato_Bed_Cap,Tomato_Price-(MAX(0,MIN(F94+INDEX(C5:C24,C94+1),Own_Labor_Hours)-MIN(F94,Own_Labor_Hours))*Farmer_Implied_Wage+(INDEX(C5:C24,C94+1)-MAX(0,MIN(F94+INDEX(C5:C24,C94+1),Own_Labor_Hours)-MIN(F94,Own_Labor_Hours)))*Temp_Wage_Per_Hour+Tomato_Fertilizer_Per_Bed),-1E+018) | H95: =IF(D94<Carrot_Bed_Cap,Carrot_Price-(MAX(0,MIN(F94+INDEX(J5:J24,D94+1),Own_Labor_Hours)-MIN(F94,Own_Labor_Hours))*Farmer_Implied_Wage+(INDEX(J5:J24,D94+1)-MAX(0,MIN(F94+INDEX(J5:J24,D94+1),Own_Labor_Hours)-MIN(F94,Own_Labor_Hours)))*Temp_Wage_Per_Hour+Carrot_Fertilizer_Per_Bed),-1E+018) | I95: =IF(E94<Mesclun_Bed_Cap,Mesclun_Price-(MAX(0,MIN(F94+INDEX(Q5:Q34,E94+1),Own_Labor_Hours)-MIN(F94,Own_Labor_Hours))*Farmer_Implied_Wage+(INDEX(Q5:Q34,E94+1)-MAX(0,MIN(F94+INDEX(Q5:Q34,E94+1),Own_Labor_Hours)-MIN(F94,Own_Labor_Hours)))*Temp_Wage_Per_Hour+Mesclun_Fertilizer_Per_Bed),-1E+018)
A96: 15 | B96: =IF(NOT(AND(MAX(G96,H96,I96)>0,C95+D95+E95<Total_Beds)),"(stopped)",IF(G96=MAX(G96,H96,I96),"Tomato",IF(H96=MAX(G96,H96,I96),"Carrot","Mesclun"))) | C96: =C95+IF(B96="Tomato",1,0) | D96: =D95+IF(B96="Carrot",1,0) | E96: =E95+IF(B96="Mesclun",1,0) | F96: =F95+IF(B96="Tomato",INDEX(C5:C24,C95+1),IF(B96="Carrot",INDEX(J5:J24,D95+1),IF(B96="Mesclun",INDEX(Q5:Q34,E95+1),0))) | G96: =IF(C95<Tomato_Bed_Cap,Tomato_Price-(MAX(0,MIN(F95+INDEX(C5:C24,C95+1),Own_Labor_Hours)-MIN(F95,Own_Labor_Hours))*Farmer_Implied_Wage+(INDEX(C5:C24,C95+1)-MAX(0,MIN(F95+INDEX(C5:C24,C95+1),Own_Labor_Hours)-MIN(F95,Own_Labor_Hours)))*Temp_Wage_Per_Hour+Tomato_Fertilizer_Per_Bed),-1E+018) | H96: =IF(D95<Carrot_Bed_Cap,Carrot_Price-(MAX(0,MIN(F95+INDEX(J5:J24,D95+1),Own_Labor_Hours)-MIN(F95,Own_Labor_Hours))*Farmer_Implied_Wage+(INDEX(J5:J24,D95+1)-MAX(0,MIN(F95+INDEX(J5:J24,D95+1),Own_Labor_Hours)-MIN(F95,Own_Labor_Hours)))*Temp_Wage_Per_Hour+Carrot_Fertilizer_Per_Bed),-1E+018) | I96: =IF(E95<Mesclun_Bed_Cap,Mesclun_Price-(MAX(0,MIN(F95+INDEX(Q5:Q34,E95+1),Own_Labor_Hours)-MIN(F95,Own_Labor_Hours))*Farmer_Implied_Wage+(INDEX(Q5:Q34,E95+1)-MAX(0,MIN(F95+INDEX(Q5:Q34,E95+1),Own_Labor_Hours)-MIN(F95,Own_Labor_Hours)))*Temp_Wage_Per_Hour+Mesclun_Fertilizer_Per_Bed),-1E+018)
A97: 16 | B97: =IF(NOT(AND(MAX(G97,H97,I97)>0,C96+D96+E96<Total_Beds)),"(stopped)",IF(G97=MAX(G97,H97,I97),"Tomato",IF(H97=MAX(G97,H97,I97),"Carrot","Mesclun"))) | C97: =C96+IF(B97="Tomato",1,0) | D97: =D96+IF(B97="Carrot",1,0) | E97: =E96+IF(B97="Mesclun",1,0) | F97: =F96+IF(B97="Tomato",INDEX(C5:C24,C96+1),IF(B97="Carrot",INDEX(J5:J24,D96+1),IF(B97="Mesclun",INDEX(Q5:Q34,E96+1),0))) | G97: =IF(C96<Tomato_Bed_Cap,Tomato_Price-(MAX(0,MIN(F96+INDEX(C5:C24,C96+1),Own_Labor_Hours)-MIN(F96,Own_Labor_Hours))*Farmer_Implied_Wage+(INDEX(C5:C24,C96+1)-MAX(0,MIN(F96+INDEX(C5:C24,C96+1),Own_Labor_Hours)-MIN(F96,Own_Labor_Hours)))*Temp_Wage_Per_Hour+Tomato_Fertilizer_Per_Bed),-1E+018) | H97: =IF(D96<Carrot_Bed_Cap,Carrot_Price-(MAX(0,MIN(F96+INDEX(J5:J24,D96+1),Own_Labor_Hours)-MIN(F96,Own_Labor_Hours))*Farmer_Implied_Wage+(INDEX(J5:J24,D96+1)-MAX(0,MIN(F96+INDEX(J5:J24,D96+1),Own_Labor_Hours)-MIN(F96,Own_Labor_Hours)))*Temp_Wage_Per_Hour+Carrot_Fertilizer_Per_Bed),-1E+018) | I97: =IF(E96<Mesclun_Bed_Cap,Mesclun_Price-(MAX(0,MIN(F96+INDEX(Q5:Q34,E96+1),Own_Labor_Hours)-MIN(F96,Own_Labor_Hours))*Farmer_Implied_Wage+(INDEX(Q5:Q34,E96+1)-MAX(0,MIN(F96+INDEX(Q5:Q34,E96+1),Own_Labor_Hours)-MIN(F96,Own_Labor_Hours)))*Temp_Wage_Per_Hour+Mesclun_Fertilizer_Per_Bed),-1E+018)
A98: 17 | B98: =IF(NOT(AND(MAX(G98,H98,I98)>0,C97+D97+E97<Total_Beds)),"(stopped)",IF(G98=MAX(G98,H98,I98),"Tomato",IF(H98=MAX(G98,H98,I98),"Carrot","Mesclun"))) | C98: =C97+IF(B98="Tomato",1,0) | D98: =D97+IF(B98="Carrot",1,0) | E98: =E97+IF(B98="Mesclun",1,0) | F98: =F97+IF(B98="Tomato",INDEX(C5:C24,C97+1),IF(B98="Carrot",INDEX(J5:J24,D97+1),IF(B98="Mesclun",INDEX(Q5:Q34,E97+1),0))) | G98: =IF(C97<Tomato_Bed_Cap,Tomato_Price-(MAX(0,MIN(F97+INDEX(C5:C24,C97+1),Own_Labor_Hours)-MIN(F97,Own_Labor_Hours))*Farmer_Implied_Wage+(INDEX(C5:C24,C97+1)-MAX(0,MIN(F97+INDEX(C5:C24,C97+1),Own_Labor_Hours)-MIN(F97,Own_Labor_Hours)))*Temp_Wage_Per_Hour+Tomato_Fertilizer_Per_Bed),-1E+018) | H98: =IF(D97<Carrot_Bed_Cap,Carrot_Price-(MAX(0,MIN(F97+INDEX(J5:J24,D97+1),Own_Labor_Hours)-MIN(F97,Own_Labor_Hours))*Farmer_Implied_Wage+(INDEX(J5:J24,D97+1)-MAX(0,MIN(F97+INDEX(J5:J24,D97+1),Own_Labor_Hours)-MIN(F97,Own_Labor_Hours)))*Temp_Wage_Per_Hour+Carrot_Fertilizer_Per_Bed),-1E+018) | I98: =IF(E97<Mesclun_Bed_Cap,Mesclun_Price-(MAX(0,MIN(F97+INDEX(Q5:Q34,E97+1),Own_Labor_Hours)-MIN(F97,Own_Labor_Hours))*Farmer_Implied_Wage+(INDEX(Q5:Q34,E97+1)-MAX(0,MIN(F97+INDEX(Q5:Q34,E97+1),Own_Labor_Hours)-MIN(F97,Own_Labor_Hours)))*Temp_Wage_Per_Hour+Mesclun_Fertilizer_Per_Bed),-1E+018)
A99: 18 | B99: =IF(NOT(AND(MAX(G99,H99,I99)>0,C98+D98+E98<Total_Beds)),"(stopped)",IF(G99=MAX(G99,H99,I99),"Tomato",IF(H99=MAX(G99,H99,I99),"Carrot","Mesclun"))) | C99: =C98+IF(B99="Tomato",1,0) | D99: =D98+IF(B99="Carrot",1,0) | E99: =E98+IF(B99="Mesclun",1,0) | F99: =F98+IF(B99="Tomato",INDEX(C5:C24,C98+1),IF(B99="Carrot",INDEX(J5:J24,D98+1),IF(B99="Mesclun",INDEX(Q5:Q34,E98+1),0))) | G99: =IF(C98<Tomato_Bed_Cap,Tomato_Price-(MAX(0,MIN(F98+INDEX(C5:C24,C98+1),Own_Labor_Hours)-MIN(F98,Own_Labor_Hours))*Farmer_Implied_Wage+(INDEX(C5:C24,C98+1)-MAX(0,MIN(F98+INDEX(C5:C24,C98+1),Own_Labor_Hours)-MIN(F98,Own_Labor_Hours)))*Temp_Wage_Per_Hour+Tomato_Fertilizer_Per_Bed),-1E+018) | H99: =IF(D98<Carrot_Bed_Cap,Carrot_Price-(MAX(0,MIN(F98+INDEX(J5:J24,D98+1),Own_Labor_Hours)-MIN(F98,Own_Labor_Hours))*Farmer_Implied_Wage+(INDEX(J5:J24,D98+1)-MAX(0,MIN(F98+INDEX(J5:J24,D98+1),Own_Labor_Hours)-MIN(F98,Own_Labor_Hours)))*Temp_Wage_Per_Hour+Carrot_Fertilizer_Per_Bed),-1E+018) | I99: =IF(E98<Mesclun_Bed_Cap,Mesclun_Price-(MAX(0,MIN(F98+INDEX(Q5:Q34,E98+1),Own_Labor_Hours)-MIN(F98,Own_Labor_Hours))*Farmer_Implied_Wage+(INDEX(Q5:Q34,E98+1)-MAX(0,MIN(F98+INDEX(Q5:Q34,E98+1),Own_Labor_Hours)-MIN(F98,Own_Labor_Hours)))*Temp_Wage_Per_Hour+Mesclun_Fertilizer_Per_Bed),-1E+018)
A100: 19 | B100: =IF(NOT(AND(MAX(G100,H100,I100)>0,C99+D99+E99<Total_Beds)),"(stopped)",IF(G100=MAX(G100,H100,I100),"Tomato",IF(H100=MAX(G100,H100,I100),"Carrot","Mesclun"))) | C100: =C99+IF(B100="Tomato",1,0) | D100: =D99+IF(B100="Carrot",1,0) | E100: =E99+IF(B100="Mesclun",1,0) | F100: =F99+IF(B100="Tomato",INDEX(C5:C24,C99+1),IF(B100="Carrot",INDEX(J5:J24,D99+1),IF(B100="Mesclun",INDEX(Q5:Q34,E99+1),0))) | G100: =IF(C99<Tomato_Bed_Cap,Tomato_Price-(MAX(0,MIN(F99+INDEX(C5:C24,C99+1),Own_Labor_Hours)-MIN(F99,Own_Labor_Hours))*Farmer_Implied_Wage+(INDEX(C5:C24,C99+1)-MAX(0,MIN(F99+INDEX(C5:C24,C99+1),Own_Labor_Hours)-MIN(F99,Own_Labor_Hours)))*Temp_Wage_Per_Hour+Tomato_Fertilizer_Per_Bed),-1E+018) | H100: =IF(D99<Carrot_Bed_Cap,Carrot_Price-(MAX(0,MIN(F99+INDEX(J5:J24,D99+1),Own_Labor_Hours)-MIN(F99,Own_Labor_Hours))*Farmer_Implied_Wage+(INDEX(J5:J24,D99+1)-MAX(0,MIN(F99+INDEX(J5:J24,D99+1),Own_Labor_Hours)-MIN(F99,Own_Labor_Hours)))*Temp_Wage_Per_Hour+Carrot_Fertilizer_Per_Bed),-1E+018) | I100: =IF(E99<Mesclun_Bed_Cap,Mesclun_Price-(MAX(0,MIN(F99+INDEX(Q5:Q34,E99+1),Own_Labor_Hours)-MIN(F99,Own_Labor_Hours))*Farmer_Implied_Wage+(INDEX(Q5:Q34,E99+1)-MAX(0,MIN(F99+INDEX(Q5:Q34,E99+1),Own_Labor_Hours)-MIN(F99,Own_Labor_Hours)))*Temp_Wage_Per_Hour+Mesclun_Fertilizer_Per_Bed),-1E+018)
A101: 20 | B101: =IF(NOT(AND(MAX(G101,H101,I101)>0,C100+D100+E100<Total_Beds)),"(stopped)",IF(G101=MAX(G101,H101,I101),"Tomato",IF(H101=MAX(G101,H101,I101),"Carrot","Mesclun"))) | C101: =C100+IF(B101="Tomato",1,0) | D101: =D100+IF(B101="Carrot",1,0) | E101: =E100+IF(B101="Mesclun",1,0) | F101: =F100+IF(B101="Tomato",INDEX(C5:C24,C100+1),IF(B101="Carrot",INDEX(J5:J24,D100+1),IF(B101="Mesclun",INDEX(Q5:Q34,E100+1),0))) | G101: =IF(C100<Tomato_Bed_Cap,Tomato_Price-(MAX(0,MIN(F100+INDEX(C5:C24,C100+1),Own_Labor_Hours)-MIN(F100,Own_Labor_Hours))*Farmer_Implied_Wage+(INDEX(C5:C24,C100+1)-MAX(0,MIN(F100+INDEX(C5:C24,C100+1),Own_Labor_Hours)-MIN(F100,Own_Labor_Hours)))*Temp_Wage_Per_Hour+Tomato_Fertilizer_Per_Bed),-1E+018) | H101: =IF(D100<Carrot_Bed_Cap,Carrot_Price-(MAX(0,MIN(F100+INDEX(J5:J24,D100+1),Own_Labor_Hours)-MIN(F100,Own_Labor_Hours))*Farmer_Implied_Wage+(INDEX(J5:J24,D100+1)-MAX(0,MIN(F100+INDEX(J5:J24,D100+1),Own_Labor_Hours)-MIN(F100,Own_Labor_Hours)))*Temp_Wage_Per_Hour+Carrot_Fertilizer_Per_Bed),-1E+018) | I101: =IF(E100<Mesclun_Bed_Cap,Mesclun_Price-(MAX(0,MIN(F100+INDEX(Q5:Q34,E100+1),Own_Labor_Hours)-MIN(F100,Own_Labor_Hours))*Farmer_Implied_Wage+(INDEX(Q5:Q34,E100+1)-MAX(0,MIN(F100+INDEX(Q5:Q34,E100+1),Own_Labor_Hours)-MIN(F100,Own_Labor_Hours)))*Temp_Wage_Per_Hour+Mesclun_Fertilizer_Per_Bed),-1E+018)
A102: 21 | B102: =IF(NOT(AND(MAX(G102,H102,I102)>0,C101+D101+E101<Total_Beds)),"(stopped)",IF(G102=MAX(G102,H102,I102),"Tomato",IF(H102=MAX(G102,H102,I102),"Carrot","Mesclun"))) | C102: =C101+IF(B102="Tomato",1,0) | D102: =D101+IF(B102="Carrot",1,0) | E102: =E101+IF(B102="Mesclun",1,0) | F102: =F101+IF(B102="Tomato",INDEX(C5:C24,C101+1),IF(B102="Carrot",INDEX(J5:J24,D101+1),IF(B102="Mesclun",INDEX(Q5:Q34,E101+1),0))) | G102: =IF(C101<Tomato_Bed_Cap,Tomato_Price-(MAX(0,MIN(F101+INDEX(C5:C24,C101+1),Own_Labor_Hours)-MIN(F101,Own_Labor_Hours))*Farmer_Implied_Wage+(INDEX(C5:C24,C101+1)-MAX(0,MIN(F101+INDEX(C5:C24,C101+1),Own_Labor_Hours)-MIN(F101,Own_Labor_Hours)))*Temp_Wage_Per_Hour+Tomato_Fertilizer_Per_Bed),-1E+018) | H102: =IF(D101<Carrot_Bed_Cap,Carrot_Price-(MAX(0,MIN(F101+INDEX(J5:J24,D101+1),Own_Labor_Hours)-MIN(F101,Own_Labor_Hours))*Farmer_Implied_Wage+(INDEX(J5:J24,D101+1)-MAX(0,MIN(F101+INDEX(J5:J24,D101+1),Own_Labor_Hours)-MIN(F101,Own_Labor_Hours)))*Temp_Wage_Per_Hour+Carrot_Fertilizer_Per_Bed),-1E+018) | I102: =IF(E101<Mesclun_Bed_Cap,Mesclun_Price-(MAX(0,MIN(F101+INDEX(Q5:Q34,E101+1),Own_Labor_Hours)-MIN(F101,Own_Labor_Hours))*Farmer_Implied_Wage+(INDEX(Q5:Q34,E101+1)-MAX(0,MIN(F101+INDEX(Q5:Q34,E101+1),Own_Labor_Hours)-MIN(F101,Own_Labor_Hours)))*Temp_Wage_Per_Hour+Mesclun_Fertilizer_Per_Bed),-1E+018)
A103: 22 | B103: =IF(NOT(AND(MAX(G103,H103,I103)>0,C102+D102+E102<Total_Beds)),"(stopped)",IF(G103=MAX(G103,H103,I103),"Tomato",IF(H103=MAX(G103,H103,I103),"Carrot","Mesclun"))) | C103: =C102+IF(B103="Tomato",1,0) | D103: =D102+IF(B103="Carrot",1,0) | E103: =E102+IF(B103="Mesclun",1,0) | F103: =F102+IF(B103="Tomato",INDEX(C5:C24,C102+1),IF(B103="Carrot",INDEX(J5:J24,D102+1),IF(B103="Mesclun",INDEX(Q5:Q34,E102+1),0))) | G103: =IF(C102<Tomato_Bed_Cap,Tomato_Price-(MAX(0,MIN(F102+INDEX(C5:C24,C102+1),Own_Labor_Hours)-MIN(F102,Own_Labor_Hours))*Farmer_Implied_Wage+(INDEX(C5:C24,C102+1)-MAX(0,MIN(F102+INDEX(C5:C24,C102+1),Own_Labor_Hours)-MIN(F102,Own_Labor_Hours)))*Temp_Wage_Per_Hour+Tomato_Fertilizer_Per_Bed),-1E+018) | H103: =IF(D102<Carrot_Bed_Cap,Carrot_Price-(MAX(0,MIN(F102+INDEX(J5:J24,D102+1),Own_Labor_Hours)-MIN(F102,Own_Labor_Hours))*Farmer_Implied_Wage+(INDEX(J5:J24,D102+1)-MAX(0,MIN(F102+INDEX(J5:J24,D102+1),Own_Labor_Hours)-MIN(F102,Own_Labor_Hours)))*Temp_Wage_Per_Hour+Carrot_Fertilizer_Per_Bed),-1E+018) | I103: =IF(E102<Mesclun_Bed_Cap,Mesclun_Price-(MAX(0,MIN(F102+INDEX(Q5:Q34,E102+1),Own_Labor_Hours)-MIN(F102,Own_Labor_Hours))*Farmer_Implied_Wage+(INDEX(Q5:Q34,E102+1)-MAX(0,MIN(F102+INDEX(Q5:Q34,E102+1),Own_Labor_Hours)-MIN(F102,Own_Labor_Hours)))*Temp_Wage_Per_Hour+Mesclun_Fertilizer_Per_Bed),-1E+018)
A104: 23 | B104: =IF(NOT(AND(MAX(G104,H104,I104)>0,C103+D103+E103<Total_Beds)),"(stopped)",IF(G104=MAX(G104,H104,I104),"Tomato",IF(H104=MAX(G104,H104,I104),"Carrot","Mesclun"))) | C104: =C103+IF(B104="Tomato",1,0) | D104: =D103+IF(B104="Carrot",1,0) | E104: =E103+IF(B104="Mesclun",1,0) | F104: =F103+IF(B104="Tomato",INDEX(C5:C24,C103+1),IF(B104="Carrot",INDEX(J5:J24,D103+1),IF(B104="Mesclun",INDEX(Q5:Q34,E103+1),0))) | G104: =IF(C103<Tomato_Bed_Cap,Tomato_Price-(MAX(0,MIN(F103+INDEX(C5:C24,C103+1),Own_Labor_Hours)-MIN(F103,Own_Labor_Hours))*Farmer_Implied_Wage+(INDEX(C5:C24,C103+1)-MAX(0,MIN(F103+INDEX(C5:C24,C103+1),Own_Labor_Hours)-MIN(F103,Own_Labor_Hours)))*Temp_Wage_Per_Hour+Tomato_Fertilizer_Per_Bed),-1E+018) | H104: =IF(D103<Carrot_Bed_Cap,Carrot_Price-(MAX(0,MIN(F103+INDEX(J5:J24,D103+1),Own_Labor_Hours)-MIN(F103,Own_Labor_Hours))*Farmer_Implied_Wage+(INDEX(J5:J24,D103+1)-MAX(0,MIN(F103+INDEX(J5:J24,D103+1),Own_Labor_Hours)-MIN(F103,Own_Labor_Hours)))*Temp_Wage_Per_Hour+Carrot_Fertilizer_Per_Bed),-1E+018) | I104: =IF(E103<Mesclun_Bed_Cap,Mesclun_Price-(MAX(0,MIN(F103+INDEX(Q5:Q34,E103+1),Own_Labor_Hours)-MIN(F103,Own_Labor_Hours))*Farmer_Implied_Wage+(INDEX(Q5:Q34,E103+1)-MAX(0,MIN(F103+INDEX(Q5:Q34,E103+1),Own_Labor_Hours)-MIN(F103,Own_Labor_Hours)))*Temp_Wage_Per_Hour+Mesclun_Fertilizer_Per_Bed),-1E+018)
A105: 24 | B105: =IF(NOT(AND(MAX(G105,H105,I105)>0,C104+D104+E104<Total_Beds)),"(stopped)",IF(G105=MAX(G105,H105,I105),"Tomato",IF(H105=MAX(G105,H105,I105),"Carrot","Mesclun"))) | C105: =C104+IF(B105="Tomato",1,0) | D105: =D104+IF(B105="Carrot",1,0) | E105: =E104+IF(B105="Mesclun",1,0) | F105: =F104+IF(B105="Tomato",INDEX(C5:C24,C104+1),IF(B105="Carrot",INDEX(J5:J24,D104+1),IF(B105="Mesclun",INDEX(Q5:Q34,E104+1),0))) | G105: =IF(C104<Tomato_Bed_Cap,Tomato_Price-(MAX(0,MIN(F104+INDEX(C5:C24,C104+1),Own_Labor_Hours)-MIN(F104,Own_Labor_Hours))*Farmer_Implied_Wage+(INDEX(C5:C24,C104+1)-MAX(0,MIN(F104+INDEX(C5:C24,C104+1),Own_Labor_Hours)-MIN(F104,Own_Labor_Hours)))*Temp_Wage_Per_Hour+Tomato_Fertilizer_Per_Bed),-1E+018) | H105: =IF(D104<Carrot_Bed_Cap,Carrot_Price-(MAX(0,MIN(F104+INDEX(J5:J24,D104+1),Own_Labor_Hours)-MIN(F104,Own_Labor_Hours))*Farmer_Implied_Wage+(INDEX(J5:J24,D104+1)-MAX(0,MIN(F104+INDEX(J5:J24,D104+1),Own_Labor_Hours)-MIN(F104,Own_Labor_Hours)))*Temp_Wage_Per_Hour+Carrot_Fertilizer_Per_Bed),-1E+018) | I105: =IF(E104<Mesclun_Bed_Cap,Mesclun_Price-(MAX(0,MIN(F104+INDEX(Q5:Q34,E104+1),Own_Labor_Hours)-MIN(F104,Own_Labor_Hours))*Farmer_Implied_Wage+(INDEX(Q5:Q34,E104+1)-MAX(0,MIN(F104+INDEX(Q5:Q34,E104+1),Own_Labor_Hours)-MIN(F104,Own_Labor_Hours)))*Temp_Wage_Per_Hour+Mesclun_Fertilizer_Per_Bed),-1E+018)
A106: 25 | B106: =IF(NOT(AND(MAX(G106,H106,I106)>0,C105+D105+E105<Total_Beds)),"(stopped)",IF(G106=MAX(G106,H106,I106),"Tomato",IF(H106=MAX(G106,H106,I106),"Carrot","Mesclun"))) | C106: =C105+IF(B106="Tomato",1,0) | D106: =D105+IF(B106="Carrot",1,0) | E106: =E105+IF(B106="Mesclun",1,0) | F106: =F105+IF(B106="Tomato",INDEX(C5:C24,C105+1),IF(B106="Carrot",INDEX(J5:J24,D105+1),IF(B106="Mesclun",INDEX(Q5:Q34,E105+1),0))) | G106: =IF(C105<Tomato_Bed_Cap,Tomato_Price-(MAX(0,MIN(F105+INDEX(C5:C24,C105+1),Own_Labor_Hours)-MIN(F105,Own_Labor_Hours))*Farmer_Implied_Wage+(INDEX(C5:C24,C105+1)-MAX(0,MIN(F105+INDEX(C5:C24,C105+1),Own_Labor_Hours)-MIN(F105,Own_Labor_Hours)))*Temp_Wage_Per_Hour+Tomato_Fertilizer_Per_Bed),-1E+018) | H106: =IF(D105<Carrot_Bed_Cap,Carrot_Price-(MAX(0,MIN(F105+INDEX(J5:J24,D105+1),Own_Labor_Hours)-MIN(F105,Own_Labor_Hours))*Farmer_Implied_Wage+(INDEX(J5:J24,D105+1)-MAX(0,MIN(F105+INDEX(J5:J24,D105+1),Own_Labor_Hours)-MIN(F105,Own_Labor_Hours)))*Temp_Wage_Per_Hour+Carrot_Fertilizer_Per_Bed),-1E+018) | I106: =IF(E105<Mesclun_Bed_Cap,Mesclun_Price-(MAX(0,MIN(F105+INDEX(Q5:Q34,E105+1),Own_Labor_Hours)-MIN(F105,Own_Labor_Hours))*Farmer_Implied_Wage+(INDEX(Q5:Q34,E105+1)-MAX(0,MIN(F105+INDEX(Q5:Q34,E105+1),Own_Labor_Hours)-MIN(F105,Own_Labor_Hours)))*Temp_Wage_Per_Hour+Mesclun_Fertilizer_Per_Bed),-1E+018)
A107: 26 | B107: =IF(NOT(AND(MAX(G107,H107,I107)>0,C106+D106+E106<Total_Beds)),"(stopped)",IF(G107=MAX(G107,H107,I107),"Tomato",IF(H107=MAX(G107,H107,I107),"Carrot","Mesclun"))) | C107: =C106+IF(B107="Tomato",1,0) | D107: =D106+IF(B107="Carrot",1,0) | E107: =E106+IF(B107="Mesclun",1,0) | F107: =F106+IF(B107="Tomato",INDEX(C5:C24,C106+1),IF(B107="Carrot",INDEX(J5:J24,D106+1),IF(B107="Mesclun",INDEX(Q5:Q34,E106+1),0))) | G107: =IF(C106<Tomato_Bed_Cap,Tomato_Price-(MAX(0,MIN(F106+INDEX(C5:C24,C106+1),Own_Labor_Hours)-MIN(F106,Own_Labor_Hours))*Farmer_Implied_Wage+(INDEX(C5:C24,C106+1)-MAX(0,MIN(F106+INDEX(C5:C24,C106+1),Own_Labor_Hours)-MIN(F106,Own_Labor_Hours)))*Temp_Wage_Per_Hour+Tomato_Fertilizer_Per_Bed),-1E+018) | H107: =IF(D106<Carrot_Bed_Cap,Carrot_Price-(MAX(0,MIN(F106+INDEX(J5:J24,D106+1),Own_Labor_Hours)-MIN(F106,Own_Labor_Hours))*Farmer_Implied_Wage+(INDEX(J5:J24,D106+1)-MAX(0,MIN(F106+INDEX(J5:J24,D106+1),Own_Labor_Hours)-MIN(F106,Own_Labor_Hours)))*Temp_Wage_Per_Hour+Carrot_Fertilizer_Per_Bed),-1E+018) | I107: =IF(E106<Mesclun_Bed_Cap,Mesclun_Price-(MAX(0,MIN(F106+INDEX(Q5:Q34,E106+1),Own_Labor_Hours)-MIN(F106,Own_Labor_Hours))*Farmer_Implied_Wage+(INDEX(Q5:Q34,E106+1)-MAX(0,MIN(F106+INDEX(Q5:Q34,E106+1),Own_Labor_Hours)-MIN(F106,Own_Labor_Hours)))*Temp_Wage_Per_Hour+Mesclun_Fertilizer_Per_Bed),-1E+018)
A108: 27 | B108: =IF(NOT(AND(MAX(G108,H108,I108)>0,C107+D107+E107<Total_Beds)),"(stopped)",IF(G108=MAX(G108,H108,I108),"Tomato",IF(H108=MAX(G108,H108,I108),"Carrot","Mesclun"))) | C108: =C107+IF(B108="Tomato",1,0) | D108: =D107+IF(B108="Carrot",1,0) | E108: =E107+IF(B108="Mesclun",1,0) | F108: =F107+IF(B108="Tomato",INDEX(C5:C24,C107+1),IF(B108="Carrot",INDEX(J5:J24,D107+1),IF(B108="Mesclun",INDEX(Q5:Q34,E107+1),0))) | G108: =IF(C107<Tomato_Bed_Cap,Tomato_Price-(MAX(0,MIN(F107+INDEX(C5:C24,C107+1),Own_Labor_Hours)-MIN(F107,Own_Labor_Hours))*Farmer_Implied_Wage+(INDEX(C5:C24,C107+1)-MAX(0,MIN(F107+INDEX(C5:C24,C107+1),Own_Labor_Hours)-MIN(F107,Own_Labor_Hours)))*Temp_Wage_Per_Hour+Tomato_Fertilizer_Per_Bed),-1E+018) | H108: =IF(D107<Carrot_Bed_Cap,Carrot_Price-(MAX(0,MIN(F107+INDEX(J5:J24,D107+1),Own_Labor_Hours)-MIN(F107,Own_Labor_Hours))*Farmer_Implied_Wage+(INDEX(J5:J24,D107+1)-MAX(0,MIN(F107+INDEX(J5:J24,D107+1),Own_Labor_Hours)-MIN(F107,Own_Labor_Hours)))*Temp_Wage_Per_Hour+Carrot_Fertilizer_Per_Bed),-1E+018) | I108: =IF(E107<Mesclun_Bed_Cap,Mesclun_Price-(MAX(0,MIN(F107+INDEX(Q5:Q34,E107+1),Own_Labor_Hours)-MIN(F107,Own_Labor_Hours))*Farmer_Implied_Wage+(INDEX(Q5:Q34,E107+1)-MAX(0,MIN(F107+INDEX(Q5:Q34,E107+1),Own_Labor_Hours)-MIN(F107,Own_Labor_Hours)))*Temp_Wage_Per_Hour+Mesclun_Fertilizer_Per_Bed),-1E+018)
A109: 28 | B109: =IF(NOT(AND(MAX(G109,H109,I109)>0,C108+D108+E108<Total_Beds)),"(stopped)",IF(G109=MAX(G109,H109,I109),"Tomato",IF(H109=MAX(G109,H109,I109),"Carrot","Mesclun"))) | C109: =C108+IF(B109="Tomato",1,0) | D109: =D108+IF(B109="Carrot",1,0) | E109: =E108+IF(B109="Mesclun",1,0) | F109: =F108+IF(B109="Tomato",INDEX(C5:C24,C108+1),IF(B109="Carrot",INDEX(J5:J24,D108+1),IF(B109="Mesclun",INDEX(Q5:Q34,E108+1),0))) | G109: =IF(C108<Tomato_Bed_Cap,Tomato_Price-(MAX(0,MIN(F108+INDEX(C5:C24,C108+1),Own_Labor_Hours)-MIN(F108,Own_Labor_Hours))*Farmer_Implied_Wage+(INDEX(C5:C24,C108+1)-MAX(0,MIN(F108+INDEX(C5:C24,C108+1),Own_Labor_Hours)-MIN(F108,Own_Labor_Hours)))*Temp_Wage_Per_Hour+Tomato_Fertilizer_Per_Bed),-1E+018) | H109: =IF(D108<Carrot_Bed_Cap,Carrot_Price-(MAX(0,MIN(F108+INDEX(J5:J24,D108+1),Own_Labor_Hours)-MIN(F108,Own_Labor_Hours))*Farmer_Implied_Wage+(INDEX(J5:J24,D108+1)-MAX(0,MIN(F108+INDEX(J5:J24,D108+1),Own_Labor_Hours)-MIN(F108,Own_Labor_Hours)))*Temp_Wage_Per_Hour+Carrot_Fertilizer_Per_Bed),-1E+018) | I109: =IF(E108<Mesclun_Bed_Cap,Mesclun_Price-(MAX(0,MIN(F108+INDEX(Q5:Q34,E108+1),Own_Labor_Hours)-MIN(F108,Own_Labor_Hours))*Farmer_Implied_Wage+(INDEX(Q5:Q34,E108+1)-MAX(0,MIN(F108+INDEX(Q5:Q34,E108+1),Own_Labor_Hours)-MIN(F108,Own_Labor_Hours)))*Temp_Wage_Per_Hour+Mesclun_Fertilizer_Per_Bed),-1E+018)
A110: 29 | B110: =IF(NOT(AND(MAX(G110,H110,I110)>0,C109+D109+E109<Total_Beds)),"(stopped)",IF(G110=MAX(G110,H110,I110),"Tomato",IF(H110=MAX(G110,H110,I110),"Carrot","Mesclun"))) | C110: =C109+IF(B110="Tomato",1,0) | D110: =D109+IF(B110="Carrot",1,0) | E110: =E109+IF(B110="Mesclun",1,0) | F110: =F109+IF(B110="Tomato",INDEX(C5:C24,C109+1),IF(B110="Carrot",INDEX(J5:J24,D109+1),IF(B110="Mesclun",INDEX(Q5:Q34,E109+1),0))) | G110: =IF(C109<Tomato_Bed_Cap,Tomato_Price-(MAX(0,MIN(F109+INDEX(C5:C24,C109+1),Own_Labor_Hours)-MIN(F109,Own_Labor_Hours))*Farmer_Implied_Wage+(INDEX(C5:C24,C109+1)-MAX(0,MIN(F109+INDEX(C5:C24,C109+1),Own_Labor_Hours)-MIN(F109,Own_Labor_Hours)))*Temp_Wage_Per_Hour+Tomato_Fertilizer_Per_Bed),-1E+018) | H110: =IF(D109<Carrot_Bed_Cap,Carrot_Price-(MAX(0,MIN(F109+INDEX(J5:J24,D109+1),Own_Labor_Hours)-MIN(F109,Own_Labor_Hours))*Farmer_Implied_Wage+(INDEX(J5:J24,D109+1)-MAX(0,MIN(F109+INDEX(J5:J24,D109+1),Own_Labor_Hours)-MIN(F109,Own_Labor_Hours)))*Temp_Wage_Per_Hour+Carrot_Fertilizer_Per_Bed),-1E+018) | I110: =IF(E109<Mesclun_Bed_Cap,Mesclun_Price-(MAX(0,MIN(F109+INDEX(Q5:Q34,E109+1),Own_Labor_Hours)-MIN(F109,Own_Labor_Hours))*Farmer_Implied_Wage+(INDEX(Q5:Q34,E109+1)-MAX(0,MIN(F109+INDEX(Q5:Q34,E109+1),Own_Labor_Hours)-MIN(F109,Own_Labor_Hours)))*Temp_Wage_Per_Hour+Mesclun_Fertilizer_Per_Bed),-1E+018)
A111: 30 | B111: =IF(NOT(AND(MAX(G111,H111,I111)>0,C110+D110+E110<Total_Beds)),"(stopped)",IF(G111=MAX(G111,H111,I111),"Tomato",IF(H111=MAX(G111,H111,I111),"Carrot","Mesclun"))) | C111: =C110+IF(B111="Tomato",1,0) | D111: =D110+IF(B111="Carrot",1,0) | E111: =E110+IF(B111="Mesclun",1,0) | F111: =F110+IF(B111="Tomato",INDEX(C5:C24,C110+1),IF(B111="Carrot",INDEX(J5:J24,D110+1),IF(B111="Mesclun",INDEX(Q5:Q34,E110+1),0))) | G111: =IF(C110<Tomato_Bed_Cap,Tomato_Price-(MAX(0,MIN(F110+INDEX(C5:C24,C110+1),Own_Labor_Hours)-MIN(F110,Own_Labor_Hours))*Farmer_Implied_Wage+(INDEX(C5:C24,C110+1)-MAX(0,MIN(F110+INDEX(C5:C24,C110+1),Own_Labor_Hours)-MIN(F110,Own_Labor_Hours)))*Temp_Wage_Per_Hour+Tomato_Fertilizer_Per_Bed),-1E+018) | H111: =IF(D110<Carrot_Bed_Cap,Carrot_Price-(MAX(0,MIN(F110+INDEX(J5:J24,D110+1),Own_Labor_Hours)-MIN(F110,Own_Labor_Hours))*Farmer_Implied_Wage+(INDEX(J5:J24,D110+1)-MAX(0,MIN(F110+INDEX(J5:J24,D110+1),Own_Labor_Hours)-MIN(F110,Own_Labor_Hours)))*Temp_Wage_Per_Hour+Carrot_Fertilizer_Per_Bed),-1E+018) | I111: =IF(E110<Mesclun_Bed_Cap,Mesclun_Price-(MAX(0,MIN(F110+INDEX(Q5:Q34,E110+1),Own_Labor_Hours)-MIN(F110,Own_Labor_Hours))*Farmer_Implied_Wage+(INDEX(Q5:Q34,E110+1)-MAX(0,MIN(F110+INDEX(Q5:Q34,E110+1),Own_Labor_Hours)-MIN(F110,Own_Labor_Hours)))*Temp_Wage_Per_Hour+Mesclun_Fertilizer_Per_Bed),-1E+018)
A112: 31 | B112: =IF(NOT(AND(MAX(G112,H112,I112)>0,C111+D111+E111<Total_Beds)),"(stopped)",IF(G112=MAX(G112,H112,I112),"Tomato",IF(H112=MAX(G112,H112,I112),"Carrot","Mesclun"))) | C112: =C111+IF(B112="Tomato",1,0) | D112: =D111+IF(B112="Carrot",1,0) | E112: =E111+IF(B112="Mesclun",1,0) | F112: =F111+IF(B112="Tomato",INDEX(C5:C24,C111+1),IF(B112="Carrot",INDEX(J5:J24,D111+1),IF(B112="Mesclun",INDEX(Q5:Q34,E111+1),0))) | G112: =IF(C111<Tomato_Bed_Cap,Tomato_Price-(MAX(0,MIN(F111+INDEX(C5:C24,C111+1),Own_Labor_Hours)-MIN(F111,Own_Labor_Hours))*Farmer_Implied_Wage+(INDEX(C5:C24,C111+1)-MAX(0,MIN(F111+INDEX(C5:C24,C111+1),Own_Labor_Hours)-MIN(F111,Own_Labor_Hours)))*Temp_Wage_Per_Hour+Tomato_Fertilizer_Per_Bed),-1E+018) | H112: =IF(D111<Carrot_Bed_Cap,Carrot_Price-(MAX(0,MIN(F111+INDEX(J5:J24,D111+1),Own_Labor_Hours)-MIN(F111,Own_Labor_Hours))*Farmer_Implied_Wage+(INDEX(J5:J24,D111+1)-MAX(0,MIN(F111+INDEX(J5:J24,D111+1),Own_Labor_Hours)-MIN(F111,Own_Labor_Hours)))*Temp_Wage_Per_Hour+Carrot_Fertilizer_Per_Bed),-1E+018) | I112: =IF(E111<Mesclun_Bed_Cap,Mesclun_Price-(MAX(0,MIN(F111+INDEX(Q5:Q34,E111+1),Own_Labor_Hours)-MIN(F111,Own_Labor_Hours))*Farmer_Implied_Wage+(INDEX(Q5:Q34,E111+1)-MAX(0,MIN(F111+INDEX(Q5:Q34,E111+1),Own_Labor_Hours)-MIN(F111,Own_Labor_Hours)))*Temp_Wage_Per_Hour+Mesclun_Fertilizer_Per_Bed),-1E+018)
A113: 32 | B113: =IF(NOT(AND(MAX(G113,H113,I113)>0,C112+D112+E112<Total_Beds)),"(stopped)",IF(G113=MAX(G113,H113,I113),"Tomato",IF(H113=MAX(G113,H113,I113),"Carrot","Mesclun"))) | C113: =C112+IF(B113="Tomato",1,0) | D113: =D112+IF(B113="Carrot",1,0) | E113: =E112+IF(B113="Mesclun",1,0) | F113: =F112+IF(B113="Tomato",INDEX(C5:C24,C112+1),IF(B113="Carrot",INDEX(J5:J24,D112+1),IF(B113="Mesclun",INDEX(Q5:Q34,E112+1),0))) | G113: =IF(C112<Tomato_Bed_Cap,Tomato_Price-(MAX(0,MIN(F112+INDEX(C5:C24,C112+1),Own_Labor_Hours)-MIN(F112,Own_Labor_Hours))*Farmer_Implied_Wage+(INDEX(C5:C24,C112+1)-MAX(0,MIN(F112+INDEX(C5:C24,C112+1),Own_Labor_Hours)-MIN(F112,Own_Labor_Hours)))*Temp_Wage_Per_Hour+Tomato_Fertilizer_Per_Bed),-1E+018) | H113: =IF(D112<Carrot_Bed_Cap,Carrot_Price-(MAX(0,MIN(F112+INDEX(J5:J24,D112+1),Own_Labor_Hours)-MIN(F112,Own_Labor_Hours))*Farmer_Implied_Wage+(INDEX(J5:J24,D112+1)-MAX(0,MIN(F112+INDEX(J5:J24,D112+1),Own_Labor_Hours)-MIN(F112,Own_Labor_Hours)))*Temp_Wage_Per_Hour+Carrot_Fertilizer_Per_Bed),-1E+018) | I113: =IF(E112<Mesclun_Bed_Cap,Mesclun_Price-(MAX(0,MIN(F112+INDEX(Q5:Q34,E112+1),Own_Labor_Hours)-MIN(F112,Own_Labor_Hours))*Farmer_Implied_Wage+(INDEX(Q5:Q34,E112+1)-MAX(0,MIN(F112+INDEX(Q5:Q34,E112+1),Own_Labor_Hours)-MIN(F112,Own_Labor_Hours)))*Temp_Wage_Per_Hour+Mesclun_Fertilizer_Per_Bed),-1E+018)
A114: 33 | B114: =IF(NOT(AND(MAX(G114,H114,I114)>0,C113+D113+E113<Total_Beds)),"(stopped)",IF(G114=MAX(G114,H114,I114),"Tomato",IF(H114=MAX(G114,H114,I114),"Carrot","Mesclun"))) | C114: =C113+IF(B114="Tomato",1,0) | D114: =D113+IF(B114="Carrot",1,0) | E114: =E113+IF(B114="Mesclun",1,0) | F114: =F113+IF(B114="Tomato",INDEX(C5:C24,C113+1),IF(B114="Carrot",INDEX(J5:J24,D113+1),IF(B114="Mesclun",INDEX(Q5:Q34,E113+1),0))) | G114: =IF(C113<Tomato_Bed_Cap,Tomato_Price-(MAX(0,MIN(F113+INDEX(C5:C24,C113+1),Own_Labor_Hours)-MIN(F113,Own_Labor_Hours))*Farmer_Implied_Wage+(INDEX(C5:C24,C113+1)-MAX(0,MIN(F113+INDEX(C5:C24,C113+1),Own_Labor_Hours)-MIN(F113,Own_Labor_Hours)))*Temp_Wage_Per_Hour+Tomato_Fertilizer_Per_Bed),-1E+018) | H114: =IF(D113<Carrot_Bed_Cap,Carrot_Price-(MAX(0,MIN(F113+INDEX(J5:J24,D113+1),Own_Labor_Hours)-MIN(F113,Own_Labor_Hours))*Farmer_Implied_Wage+(INDEX(J5:J24,D113+1)-MAX(0,MIN(F113+INDEX(J5:J24,D113+1),Own_Labor_Hours)-MIN(F113,Own_Labor_Hours)))*Temp_Wage_Per_Hour+Carrot_Fertilizer_Per_Bed),-1E+018) | I114: =IF(E113<Mesclun_Bed_Cap,Mesclun_Price-(MAX(0,MIN(F113+INDEX(Q5:Q34,E113+1),Own_Labor_Hours)-MIN(F113,Own_Labor_Hours))*Farmer_Implied_Wage+(INDEX(Q5:Q34,E113+1)-MAX(0,MIN(F113+INDEX(Q5:Q34,E113+1),Own_Labor_Hours)-MIN(F113,Own_Labor_Hours)))*Temp_Wage_Per_Hour+Mesclun_Fertilizer_Per_Bed),-1E+018)
A115: 34 | B115: =IF(NOT(AND(MAX(G115,H115,I115)>0,C114+D114+E114<Total_Beds)),"(stopped)",IF(G115=MAX(G115,H115,I115),"Tomato",IF(H115=MAX(G115,H115,I115),"Carrot","Mesclun"))) | C115: =C114+IF(B115="Tomato",1,0) | D115: =D114+IF(B115="Carrot",1,0) | E115: =E114+IF(B115="Mesclun",1,0) | F115: =F114+IF(B115="Tomato",INDEX(C5:C24,C114+1),IF(B115="Carrot",INDEX(J5:J24,D114+1),IF(B115="Mesclun",INDEX(Q5:Q34,E114+1),0))) | G115: =IF(C114<Tomato_Bed_Cap,Tomato_Price-(MAX(0,MIN(F114+INDEX(C5:C24,C114+1),Own_Labor_Hours)-MIN(F114,Own_Labor_Hours))*Farmer_Implied_Wage+(INDEX(C5:C24,C114+1)-MAX(0,MIN(F114+INDEX(C5:C24,C114+1),Own_Labor_Hours)-MIN(F114,Own_Labor_Hours)))*Temp_Wage_Per_Hour+Tomato_Fertilizer_Per_Bed),-1E+018) | H115: =IF(D114<Carrot_Bed_Cap,Carrot_Price-(MAX(0,MIN(F114+INDEX(J5:J24,D114+1),Own_Labor_Hours)-MIN(F114,Own_Labor_Hours))*Farmer_Implied_Wage+(INDEX(J5:J24,D114+1)-MAX(0,MIN(F114+INDEX(J5:J24,D114+1),Own_Labor_Hours)-MIN(F114,Own_Labor_Hours)))*Temp_Wage_Per_Hour+Carrot_Fertilizer_Per_Bed),-1E+018) | I115: =IF(E114<Mesclun_Bed_Cap,Mesclun_Price-(MAX(0,MIN(F114+INDEX(Q5:Q34,E114+1),Own_Labor_Hours)-MIN(F114,Own_Labor_Hours))*Farmer_Implied_Wage+(INDEX(Q5:Q34,E114+1)-MAX(0,MIN(F114+INDEX(Q5:Q34,E114+1),Own_Labor_Hours)-MIN(F114,Own_Labor_Hours)))*Temp_Wage_Per_Hour+Mesclun_Fertilizer_Per_Bed),-1E+018)
...

Sheet Solver
A1: Solver — Decision Variables & Setup
A2: Values below are the validated optimum (exhaustive search + confirmed by the greedy walk on Calculations — see spec §6). Change them to explore other allocations.
A4: Decision Variables (Solver's "changing cells")
A6: Beds — Tomato | C6: 10
A7: Beds — Carrot | C7: 20
A8: Beds — Mesclun | C8: 30
A9: Temp workers hired | C9: 4
A11: Objective (Solver's "Set Objective" cell) — Maximize | C11: =Calculations!$E$53
A13: Constraints
A14: • Beds_Tomato <= Tomato_Bed_Cap
A15: • Beds_Carrot <= Carrot_Bed_Cap
A16: • Beds_Mesclun <= Mesclun_Bed_Cap
A17: • Beds_Tomato + Beds_Carrot + Beds_Mesclun <= Total_Beds
A18: • Total labor hours needed <= Own_Labor_Hours + Temp_Workers_Hired x Temp_Worker_Hours
A19: • Temp_Workers_Hired >= workers actually needed to cover the hours (no under-hiring)
A20: • 0 <= Temp_Workers_Hired <= Temp_Worker_Max, integer
A21: • All beds >= 0, integer
A23: Live constraint checks (linked from Calculations)
A24: Tomato beds <= cap | C24: =Calculations!$E$56
A25: Carrot beds <= cap | C25: =Calculations!$E$57
A26: Mesclun beds <= cap | C26: =Calculations!$E$58
A27: Total beds <= Total_Beds | C27: =Calculations!$E$59
A28: Temp workers valid (integer 0-4) | C28: =Calculations!$E$60
A29: Labor hours covered | C29: =Calculations!$E$61
A30: Not under-hired | C30: =Calculations!$E$62
A32: To re-run in Excel: Data tab > Solver > Set Objective = C11, To: Max, By Changing Variable Cells = C6:C9, Add the constraints above, Solving Method = Evolutionary or GRG Nonlinear (this cost model is smooth, no lumpy jump -- see spec sec 5), then Solve.

Sheet Notes
A1: Notes — Market Garden Bed Allocation Model (v1.5)
A3: What this model does
A4: Chooses how many of 64 beds to plant with tomatoes, carrots, and mesclun (one 36-week season, no mid-season replanting), and how many temp workers to hire, to maximize season profit. See capabilities/marginal-analysis/spec.md for the full spec, including section 6's validation log.
A6: Data sources
A7: - docs/briefs/perfect-competition-brief.md -- problem framing, fixed/chosen variables, assumptions, hypothesis.
A8: - Case materials (crop economics table) -- per-crop price, fertilizer $/bed, base labor hrs/wk/bed, diminishing-returns rate.
A9: - Farm Profit Lab (adamwstauffer.github.io/ai-lms/farmlab.html) -- validated the labor-wage tiering and confirmed the acceptance criteria (spec sec 6).
A11: Labor cost -- corrected in v1.3, wage inputs corrected again in v1.5
A12: The farmer's first 720 hours (shared across all three crops) are priced at Farmer_Implied_Wage -- the EXPENSIVE tier, not free. Hours beyond 720 drop to Temp_Wage_Per_Hour -- the CHEAP tier. There is no $0 tier and no separate Farmer_Salary fixed cost; her compensation is captured entirely through the per-hour Farmer_Implied_Wage charge.
A13: v1.5: Farmer_Implied_Wage and Temp_Wage_Per_Hour are formulas on Inputs (=Farmer_Season_Salary/2/Own_Labor_Hours = $34.7222.../hr, and =Temp_Worker_Flat_Cost/Temp_Worker_Hours = $17.3611.../hr), not the case materials' rounded, displayed values ($34.72 / $17.36). Entering the rounded values directly had moved season profit by several dollars -- small enough to hide inside a tolerance band, which is exactly why that tolerance was removed rather than kept (spec sec 6, v1.5 defect record).
A14: Open item: the brief states a $25,000-per-temp-worker lumpy hiring fee. The validated Farm Profit Lab's own P&L does not charge it -- Temp_Workers_Hired there is an informational feasibility count only. This model matches the validated (no-fee) version, since that's what reproduces the acceptance criteria. Worth confirming with Adam before treating as settled.
A16: Validated result
... A28: AI-assisted build -- logged in prompt-log.md per docs/standards/excel-formatting.md.
